Workbook

Sheet Cover
B2: GYM & FITNESS STUDIO — 3-YEAR FINANCIAL MODEL
B3: Boutique Gym · GCC Market · Base Case Build, 2026
B5: OVERVIEW
B6: Bottom-up 3-year financial model for a boutique gym. Starts from the local catchment population (Catchment → Active Gym-Goers → SAM → Members) and builds through membership tiers, personal training and class packs to a monthly P&L and EBITDA. Yellow-highlighted cells are analyst estimates — adjust them to stress-test the model.
B8: NAVIGATE THE MODEL
B9: 1 · Assumptions All inputs — catchment market, tier pricing, churn, growth targets, cost rates. Yellow = analyst estimate.
B10: 2 · Member Build Monthly membership base for 36 months — joins, churn, tier split, PT and class attach rates.
B11: 3 · Monthly P&L Three revenue streams (memberships, personal training, class packs), staff and facility costs to EBITDA.
B12: 4 · Annual Summary 3-year P&L rollup, revenue mix, funding requirement and break-even.
B14: COLOUR LEGEND
B15: Blue text → Given input (market data or published rate)
B16: Blue text + yellow background → Analyst estimate — change to stress-test
... B18: Green text → Link pulling from another tab — do not overwrite

Sheet Assumptions
A1: GYM & FITNESS STUDIO — MODEL ASSUMPTIONS
A2: Blue = given (market data / rate card). Yellow = analyst estimate — change to stress-test. Black = formula, do not edit.
A4: MARKET CONTEXT — LOCAL CATCHMENT
A5: Catchment population within 15 min drive | B5: 120000 | E5: How many people live within a realistic drive of the gym?
A6: Regular exercisers — % of catchment | B6: 0.22 | E6: What share of the catchment exercises at least weekly?
A7: Active gym-goers — derived | B7: =B5*B6 -> 26400 | E7: People in range who train regularly. (population × exerciser rate)
A8: Willing to pay boutique rates — SAM % | B8: 0.3 | E8: Share of gym-goers open to a boutique membership over a budget chain.
A9: SAM — addressable members | B9: =B7*B8 -> 7920 | E9: Our total addressable membership pool.
A11: MEMBERSHIP FUNNEL
A12: Members — Month 1 opening | B12: 60 | E12: Founding members signed at launch.
A13: Target members by year-end [Y1 | Y2 | Y3] | B13: 220 | C13: 420 | D13: 600 | E13: How many active members do we want at the end of each year?
A14: Monthly member growth rate — derived [Y1 | Y2 | Y3] | B14: =(B13/B12)^(1/12)-1 -> 0.11435257 | C14: =(C13/B13)^(1/12)-1 -> 0.055363859 | D14: =(D13/C13)^(1/12)-1 -> 0.030169047 | E14: Monthly compounding rate needed to hit each year-end target.
A15: Monthly churn rate | B15: 0.05 | E15: Share of members who cancel each month. Joins must outpace this.
A17: PRICING — RATE CARD
A18: Standard membership — monthly fee | B18: 350 | E18: Gym floor + group classes.
A19: Premium membership — monthly fee | B19: 550 | E19: All access + recovery zone + guest passes.
A20: Premium members — % of base | B20: 0.3 | E20: What share of members upgrade to Premium?
A21: PT session — price | B21: 180 | E21: One-on-one personal training, per session.
A22: PT sessions per member per month — average | B22: 0.8 | E22: Averaged across the whole base; most buy none, some buy weekly.
A23: Class pack — price (10 classes, non-members) | B23: 400 | E23: Drop-in class product for non-members.
A24: Class packs sold per month — per 100 members | B24: 6 | E24: Non-member demand scales with the community around the gym.
A26: OPERATING COSTS
A27: Rent — monthly | B27: 45000 | E27: Warehouse-format unit, prime-adjacent location.
A28: Head coach — monthly salary | B28: 14000 | E28: Leads programming and the coaching team.
A29: Coaches — monthly salary each | B29: 8000 | E29: Full-time floor coaches.
A30: Coaches — headcount [Y1 | Y2 | Y3] | B30: 3 | C30: 5 | D30: 7 | E30: Scales with the member base.
A31: PT trainer payout — % of PT revenue | B31: 0.45 | E31: Revenue share paid to trainers on PT sessions.
A32: Front desk & ops staff — monthly total | B32: 11000 | E32: Reception, cleaning, ops.
A33: Utilities & consumables — monthly | B33: 7000 | E33: Power, water, towels, supplies.
A34: Software & payments — monthly | B34: 2000 | E34: Booking app, access control, payment fees.
A35: Marketing — cost per new member acquired | B35: 250 | E35: Blended CAC across paid, referral and community.
A37: ONE-TIME CAPEX (pre-launch)
A38: Equipment & rig fit-out | B38: 420000
A39: Interiors, changing rooms & branding | B39: 180000
A40: Pre-launch marketing & founding-member drive | B40: 40000
A41: Total One-Time Capex — derived | B41: =SUM(B38:B40) -> 640000

Sheet Member Build
A1: GYM & FITNESS STUDIO | MEMBER BUILD
A2: 36-month membership base: joins, churn, tier split and attach rates. Green = pulls from Assumptions.
A4: Month | B4: 1 | C4: 2 | D4: 3 | E4: 4 | F4: 5 | G4: 6 | H4: 7 | I4: 8 | J4: 9 | K4: 10 | L4: 11 | M4: 12 | N4: 13 | O4: 14 | P4: 15 | Q4: 16 | R4: 17 | S4: 18 | T4: 19 | U4: 20 | V4: 21 | W4: 22 | X4: 23 | Y4: 24 | Z4: 25 | AA4: 26 | AB4: 27 | AC4: 28 | AD4: 29 | AE4: 30 | AF4: 31 | AG4: 32 | AH4: 33 | AI4: 34 | AJ4: 35 | AK4: 36
A5: Year | B5: Y1 | C5: Y1 | D5: Y1 | E5: Y1 | F5: Y1 | G5: Y1 | H5: Y1 | I5: Y1 | J5: Y1 | K5: Y1 | L5: Y1 | M5: Y1 | N5: Y2 | O5: Y2 | P5: Y2 | Q5: Y2 | R5: Y2 | S5: Y2 | T5: Y2 | U5: Y2 | V5: Y2 | W5: Y2 | X5: Y2 | Y5: Y2 | Z5: Y3 | AA5: Y3 | AB5: Y3 | AC5: Y3 | AD5: Y3 | AE5: Y3 | AF5: Y3 | AG5: Y3 | AH5: Y3 | AI5: Y3 | AJ5: Y3 | AK5: Y3
A7: Opening members | B7: =Assumptions!B12 -> 60 | C7: =B10 -> 66.861154 | D7: =C10 -> 74.506899 | E7: =D10 -> 83.026955 | F7: =E10 -> 92.5213 | G7: =F10 -> 103.10135 | H7: =G10 -> 114.89125 | I7: =H10 -> 128.02936 | J7: =I10 -> 142.66985 | ... AK7: =AJ10 -> 582.42868
A8: New joins (growth + replacing churn) | B8: =B7*(Assumptions!B$14+Assumptions!$B$15) -> 9.8611542 | C8: =C7*(Assumptions!B$14+Assumptions!$B$15) -> 10.988803 | D8: =D7*(Assumptions!B$14+Assumptions!$B$15) -> 12.2454 | E8: =E7*(Assumptions!B$14+Assumptions!$B$15) -> 13.645693 | F8: =F7*(Assumptions!B$14+Assumptions!$B$15) -> 15.206114 | G8: =G7*(Assumptions!B$14+Assumptions!$B$15) -> 16.944972 | H8: =H7*(Assumptions!B$14+Assumptions!$B$15) -> 18.882673 | I8: =I7*(Assumptions!B$14+Assumptions!$B$15) -> 21.041955 | J8: =J7*(Assumptions!B$14+Assumptions!$B$15) -> 23.448157 | K8: =K7*(Assumptions!B$14+Assumptions!$B$15) -> 26.129514 | L8: =L7*(Assumptions!B$14+Assumptions!$B$15) -> 29.117491 | M8: =M7*(Assumptions!B$14+Assumptions!$B$15) -> 32.44715 | N8: =N7*(Assumptions!C$14+Assumptions!$B$15) -> 23.180049 | O8: =O7*(Assumptions!C$14+Assumptions!$B$15) -> 24.463386 | P8: =P7*(Assumptions!C$14+Assumptions!$B$15) -> 25.817773 | Q8: =Q7*(Assumptions!C$14+Assumptions!$B$15) -> 27.247145 | R8: =R7*(Assumptions!C$14+Assumptions!$B$15) -> 28.755652 | S8: =S7*(Assumptions!C$14+Assumptions!$B$15) -> 30.347676 | T8: =T7*(Assumptions!C$14+Assumptions!$B$15) -> 32.02784 | U8: =U7*(Assumptions!C$14+Assumptions!$B$15) -> 33.801025 | V8: =V7*(Assumptions!C$14+Assumptions!$B$15) -> 35.67238 | W8: =W7*(Assumptions!C$14+Assumptions!$B$15) -> 37.647341 | X8: =X7*(Assumptions!C$14+Assumptions!$B$15) -> 39.731643 | Y8: =Y7*(Assumptions!C$14+Assumptions!$B$15) -> 41.93134 | Z8: =Z7*(Assumptions!D$14+Assumptions!$B$15) -> 33.671 | AA8: =AA7*(Assumptions!D$14+Assumptions!$B$15) -> 34.686822 | AB8: =AB7*(Assumptions!D$14+Assumptions!$B$15) -> 35.73329 | AC8: =AC7*(Assumptions!D$14+Assumptions!$B$15) -> 36.811329 | AD8: =AD7*(Assumptions!D$14+Assumptions!$B$15) -> 37.921892 | AE8: =AE7*(Assumptions!D$14+Assumptions!$B$15) -> 39.065959 | AF8: =AF7*(Assumptions!D$14+Assumptions!$B$15) -> 40.244542 | AG8: =AG7*(Assumptions!D$14+Assumptions!$B$15) -> 41.458682 | AH8: =AH7*(Assumptions!D$14+Assumptions!$B$15) -> 42.709451 | AI8: =AI7*(Assumptions!D$14+Assumptions!$B$15) -> 43.997954 | AJ8: =AJ7*(Assumptions!D$14+Assumptions!$B$15) -> 45.32533 | AK8: =AK7*(Assumptions!D$14+Assumptions!$B$15) -> 46.692752
A9: Churned members | B9: =-B7*Assumptions!$B$15 -> -3 | C9: =-C7*Assumptions!$B$15 -> -3.3430577 | D9: =-D7*Assumptions!$B$15 -> -3.725345 | E9: =-E7*Assumptions!$B$15 -> -4.1513477 | F9: =-F7*Assumptions!$B$15 -> -4.626065 | G9: =-G7*Assumptions!$B$15 -> -5.1550674 | H9: =-H7*Assumptions!$B$15 -> -5.7445626 | I9: =-I7*Assumptions!$B$15 -> -6.4014682 | ... AK9: =-AK7*Assumptions!$B$15 -> -29.121434
A10: Closing members | B10: =B7+B8+B9 -> 66.861154 | C10: =C7+C8+C9 -> 74.506899 | D10: =D7+D8+D9 -> 83.026955 | E10: =E7+E8+E9 -> 92.5213 | F10: =F7+F8+F9 -> 103.10135 | G10: =G7+G8+G9 -> 114.89125 | H10: =H7+H8+H9 -> 128.02936 | I10: =I7+I8+I9 -> 142.66985 | ... AK10: =AK7+AK8+AK9 -> 600
A12: Premium members | B12: =B10*Assumptions!$B$20 -> 20.058346 | C12: =C10*Assumptions!$B$20 -> 22.35207 | D12: =D10*Assumptions!$B$20 -> 24.908086 | E12: =E10*Assumptions!$B$20 -> 27.75639 | F12: =F10*Assumptions!$B$20 -> 30.930405 | G12: =G10*Assumptions!$B$20 -> 34.467376 | H12: =H10*Assumptions!$B$20 -> 38.408809 | I12: =I10*Assumptions!$B$20 -> 42.800955 | ... AK12: =AK10*Assumptions!$B$20 -> 180
A13: Standard members | B13: =B10-B12 -> 46.802808 | C13: =C10-C12 -> 52.154829 | D13: =D10-D12 -> 58.118868 | E13: =E10-E12 -> 64.76491 | F13: =F10-F12 -> 72.170944 | G13: =G10-G12 -> 80.423877 | H13: =H10-H12 -> 89.620554 | I13: =I10-I12 -> 99.868895 | ... AK13: =AK10-AK12 -> 420
A15: PT sessions delivered | B15: =B10*Assumptions!$B$22 -> 53.488923 | C15: =C10*Assumptions!$B$22 -> 59.605519 | D15: =D10*Assumptions!$B$22 -> 66.421564 | E15: =E10*Assumptions!$B$22 -> 74.01704 | F15: =F10*Assumptions!$B$22 -> 82.481079 | G15: =G10*Assumptions!$B$22 -> 91.913002 | H15: =H10*Assumptions!$B$22 -> 102.42349 | I15: =I10*Assumptions!$B$22 -> 114.13588 | ... AK15: =AK10*Assumptions!$B$22 -> 480
A16: Class packs sold (non-members) | B16: =B10/100*Assumptions!$B$24 -> 4.0116693 | C16: =C10/100*Assumptions!$B$24 -> 4.4704139 | D16: =D10/100*Assumptions!$B$24 -> 4.9816173 | E16: =E10/100*Assumptions!$B$24 -> 5.551278 | F16: =F10/100*Assumptions!$B$24 -> 6.1860809 | G16: =G10/100*Assumptions!$B$24 -> 6.8934752 | H16: =H10/100*Assumptions!$B$24 -> 7.6817618 | I16: =I10/100*Assumptions!$B$24 -> 8.560191 | ... AK16: =AK10/100*Assumptions!$B$24 -> 36

Sheet Monthly P&L
A1: GYM & FITNESS STUDIO | MONTHLY P&L
A2: Three revenue streams to EBITDA, 36 months. Green = pulls from Member Build / Assumptions.
A4: Month | B4: 1 | C4: 2 | D4: 3 | E4: 4 | F4: 5 | G4: 6 | H4: 7 | I4: 8 | J4: 9 | K4: 10 | L4: 11 | M4: 12 | N4: 13 | O4: 14 | P4: 15 | Q4: 16 | R4: 17 | S4: 18 | T4: 19 | U4: 20 | V4: 21 | W4: 22 | X4: 23 | Y4: 24 | Z4: 25 | AA4: 26 | AB4: 27 | AC4: 28 | AD4: 29 | AE4: 30 | AF4: 31 | AG4: 32 | AH4: 33 | AI4: 34 | AJ4: 35 | AK4: 36
A5: Year | B5: Y1 | C5: Y1 | D5: Y1 | E5: Y1 | F5: Y1 | G5: Y1 | H5: Y1 | I5: Y1 | J5: Y1 | K5: Y1 | L5: Y1 | M5: Y1 | N5: Y2 | O5: Y2 | P5: Y2 | Q5: Y2 | R5: Y2 | S5: Y2 | T5: Y2 | U5: Y2 | V5: Y2 | W5: Y2 | X5: Y2 | Y5: Y2 | Z5: Y3 | AA5: Y3 | AB5: Y3 | AC5: Y3 | AD5: Y3 | AE5: Y3 | AF5: Y3 | AG5: Y3 | AH5: Y3 | AI5: Y3 | AJ5: Y3 | AK5: Y3
A7: REVENUE
A8: Standard memberships | B8: ='Member Build'!B13*Assumptions!$B$18 -> 16380.983 | C8: ='Member Build'!C13*Assumptions!$B$18 -> 18254.19 | D8: ='Member Build'!D13*Assumptions!$B$18 -> 20341.604 | E8: ='Member Build'!E13*Assumptions!$B$18 -> 22667.719 | F8: ='Member Build'!F13*Assumptions!$B$18 -> 25259.83 | G8: ='Member Build'!G13*Assumptions!$B$18 -> 28148.357 | H8: ='Member Build'!H13*Assumptions!$B$18 -> 31367.194 | I8: ='Member Build'!I13*Assumptions!$B$18 -> 34954.113 | ... AK8: ='Member Build'!AK13*Assumptions!$B$18 -> 147000
A9: Premium memberships | B9: ='Member Build'!B12*Assumptions!$B$19 -> 11032.09 | C9: ='Member Build'!C12*Assumptions!$B$19 -> 12293.638 | D9: ='Member Build'!D12*Assumptions!$B$19 -> 13699.447 | E9: ='Member Build'!E12*Assumptions!$B$19 -> 15266.015 | F9: ='Member Build'!F12*Assumptions!$B$19 -> 17011.723 | G9: ='Member Build'!G12*Assumptions!$B$19 -> 18957.057 | H9: ='Member Build'!H12*Assumptions!$B$19 -> 21124.845 | I9: ='Member Build'!I12*Assumptions!$B$19 -> 23540.525 | ... AK9: ='Member Build'!AK12*Assumptions!$B$19 -> 99000
A10: Personal training | B10: ='Member Build'!B15*Assumptions!$B$21 -> 9628.0062 | C10: ='Member Build'!C15*Assumptions!$B$21 -> 10728.993 | D10: ='Member Build'!D15*Assumptions!$B$21 -> 11955.881 | E10: ='Member Build'!E15*Assumptions!$B$21 -> 13323.067 | F10: ='Member Build'!F15*Assumptions!$B$21 -> 14846.594 | G10: ='Member Build'!G15*Assumptions!$B$21 -> 16544.34 | H10: ='Member Build'!H15*Assumptions!$B$21 -> 18436.228 | I10: ='Member Build'!I15*Assumptions!$B$21 -> 20544.458 | ... AK10: ='Member Build'!AK15*Assumptions!$B$21 -> 86400
A11: Class packs | B11: ='Member Build'!B16*Assumptions!$B$23 -> 1604.6677 | C11: ='Member Build'!C16*Assumptions!$B$23 -> 1788.1656 | D11: ='Member Build'!D16*Assumptions!$B$23 -> 1992.6469 | E11: ='Member Build'!E16*Assumptions!$B$23 -> 2220.5112 | F11: ='Member Build'!F16*Assumptions!$B$23 -> 2474.4324 | G11: ='Member Build'!G16*Assumptions!$B$23 -> 2757.3901 | H11: ='Member Build'!H16*Assumptions!$B$23 -> 3072.7047 | I11: ='Member Build'!I16*Assumptions!$B$23 -> 3424.0764 | ... AK11: ='Member Build'!AK16*Assumptions!$B$23 -> 14400
A12: TOTAL REVENUE | B12: =SUM(B8:B11) -> 38645.747 | C12: =SUM(C8:C11) -> 43064.988 | D12: =SUM(D8:D11) -> 47989.58 | E12: =SUM(E8:E11) -> 53477.312 | F12: =SUM(F8:F11) -> 59592.58 | G12: =SUM(G8:G11) -> 66407.144 | H12: =SUM(H8:H11) -> 74000.972 | I12: =SUM(I8:I11) -> 82463.173 | ... AK12: =SUM(AK8:AK11) -> 346800
A14: DIRECT & OPERATING COSTS
A15: Rent | B15: =-Assumptions!$B$27 -> -45000 | C15: =-Assumptions!$B$27 -> -45000 | D15: =-Assumptions!$B$27 -> -45000 | E15: =-Assumptions!$B$27 -> -45000 | F15: =-Assumptions!$B$27 -> -45000 | G15: =-Assumptions!$B$27 -> -45000 | H15: =-Assumptions!$B$27 -> -45000 | I15: =-Assumptions!$B$27 -> -45000 | ... AK15: =-Assumptions!$B$27 -> -45000
A16: Head coach | B16: =-Assumptions!$B$28 -> -14000 | C16: =-Assumptions!$B$28 -> -14000 | D16: =-Assumptions!$B$28 -> -14000 | E16: =-Assumptions!$B$28 -> -14000 | F16: =-Assumptions!$B$28 -> -14000 | G16: =-Assumptions!$B$28 -> -14000 | H16: =-Assumptions!$B$28 -> -14000 | I16: =-Assumptions!$B$28 -> -14000 | ... AK16: =-Assumptions!$B$28 -> -14000
A17: Coaching team | B17: =-Assumptions!B$30*Assumptions!$B$29 -> -24000 | C17: =-Assumptions!B$30*Assumptions!$B$29 -> -24000 | D17: =-Assumptions!B$30*Assumptions!$B$29 -> -24000 | E17: =-Assumptions!B$30*Assumptions!$B$29 -> -24000 | F17: =-Assumptions!B$30*Assumptions!$B$29 -> -24000 | G17: =-Assumptions!B$30*Assumptions!$B$29 -> -24000 | H17: =-Assumptions!B$30*Assumptions!$B$29 -> -24000 | I17: =-Assumptions!B$30*Assumptions!$B$29 -> -24000 | J17: =-Assumptions!B$30*Assumptions!$B$29 -> -24000 | K17: =-Assumptions!B$30*Assumptions!$B$29 -> -24000 | L17: =-Assumptions!B$30*Assumptions!$B$29 -> -24000 | M17: =-Assumptions!B$30*Assumptions!$B$29 -> -24000 | N17: =-Assumptions!C$30*Assumptions!$B$29 -> -40000 | O17: =-Assumptions!C$30*Assumptions!$B$29 -> -40000 | P17: =-Assumptions!C$30*Assumptions!$B$29 -> -40000 | Q17: =-Assumptions!C$30*Assumptions!$B$29 -> -40000 | R17: =-Assumptions!C$30*Assumptions!$B$29 -> -40000 | S17: =-Assumptions!C$30*Assumptions!$B$29 -> -40000 | T17: =-Assumptions!C$30*Assumptions!$B$29 -> -40000 | U17: =-Assumptions!C$30*Assumptions!$B$29 -> -40000 | V17: =-Assumptions!C$30*Assumptions!$B$29 -> -40000 | W17: =-Assumptions!C$30*Assumptions!$B$29 -> -40000 | X17: =-Assumptions!C$30*Assumptions!$B$29 -> -40000 | Y17: =-Assumptions!C$30*Assumptions!$B$29 -> -40000 | Z17: =-Assumptions!D$30*Assumptions!$B$29 -> -56000 | AA17: =-Assumptions!D$30*Assumptions!$B$29 -> -56000 | AB17: =-Assumptions!D$30*Assumptions!$B$29 -> -56000 | AC17: =-Assumptions!D$30*Assumptions!$B$29 -> -56000 | AD17: =-Assumptions!D$30*Assumptions!$B$29 -> -56000 | AE17: =-Assumptions!D$30*Assumptions!$B$29 -> -56000 | AF17: =-Assumptions!D$30*Assumptions!$B$29 -> -56000 | AG17: =-Assumptions!D$30*Assumptions!$B$29 -> -56000 | AH17: =-Assumptions!D$30*Assumptions!$B$29 -> -56000 | AI17: =-Assumptions!D$30*Assumptions!$B$29 -> -56000 | AJ17: =-Assumptions!D$30*Assumptions!$B$29 -> -56000 | AK17: =-Assumptions!D$30*Assumptions!$B$29 -> -56000
A18: PT trainer payout | B18: =-B10*Assumptions!$B$31 -> -4332.6028 | C18: =-C10*Assumptions!$B$31 -> -4828.0471 | D18: =-D10*Assumptions!$B$31 -> -5380.1467 | E18: =-E10*Assumptions!$B$31 -> -5995.3803 | F18: =-F10*Assumptions!$B$31 -> -6680.9674 | G18: =-G10*Assumptions!$B$31 -> -7444.9532 | H18: =-H10*Assumptions!$B$31 -> -8296.3027 | I18: =-I10*Assumptions!$B$31 -> -9245.0063 | ... AK18: =-AK10*Assumptions!$B$31 -> -38880
A19: Front desk & ops | B19: =-Assumptions!$B$32 -> -11000 | C19: =-Assumptions!$B$32 -> -11000 | D19: =-Assumptions!$B$32 -> -11000 | E19: =-Assumptions!$B$32 -> -11000 | F19: =-Assumptions!$B$32 -> -11000 | G19: =-Assumptions!$B$32 -> -11000 | H19: =-Assumptions!$B$32 -> -11000 | I19: =-Assumptions!$B$32 -> -11000 | ... AK19: =-Assumptions!$B$32 -> -11000
A20: Utilities & consumables | B20: =-Assumptions!$B$33 -> -7000 | C20: =-Assumptions!$B$33 -> -7000 | D20: =-Assumptions!$B$33 -> -7000 | E20: =-Assumptions!$B$33 -> -7000 | F20: =-Assumptions!$B$33 -> -7000 | G20: =-Assumptions!$B$33 -> -7000 | H20: =-Assumptions!$B$33 -> -7000 | I20: =-Assumptions!$B$33 -> -7000 | ... AK20: =-Assumptions!$B$33 -> -7000
A21: Software & payments | B21: =-Assumptions!$B$34 -> -2000 | C21: =-Assumptions!$B$34 -> -2000 | D21: =-Assumptions!$B$34 -> -2000 | E21: =-Assumptions!$B$34 -> -2000 | F21: =-Assumptions!$B$34 -> -2000 | G21: =-Assumptions!$B$34 -> -2000 | H21: =-Assumptions!$B$34 -> -2000 | I21: =-Assumptions!$B$34 -> -2000 | ... AK21: =-Assumptions!$B$34 -> -2000
A22: Marketing (new-member CAC) | B22: =-'Member Build'!B8*Assumptions!$B$35 -> -2465.2886 | C22: =-'Member Build'!C8*Assumptions!$B$35 -> -2747.2006 | D22: =-'Member Build'!D8*Assumptions!$B$35 -> -3061.3501 | E22: =-'Member Build'!E8*Assumptions!$B$35 -> -3411.4233 | F22: =-'Member Build'!F8*Assumptions!$B$35 -> -3801.5284 | G22: =-'Member Build'!G8*Assumptions!$B$35 -> -4236.2429 | H22: =-'Member Build'!H8*Assumptions!$B$35 -> -4720.6682 | I22: =-'Member Build'!I8*Assumptions!$B$35 -> -5260.4887 | ... AK22: =-'Member Build'!AK8*Assumptions!$B$35 -> -11673.188
A23: TOTAL COSTS | B23: =SUM(B15:B22) -> -109797.89 | C23: =SUM(C15:C22) -> -110575.25 | D23: =SUM(D15:D22) -> -111441.5 | E23: =SUM(E15:E22) -> -112406.8 | F23: =SUM(F15:F22) -> -113482.5 | G23: =SUM(G15:G22) -> -114681.2 | H23: =SUM(H15:H22) -> -116016.97 | I23: =SUM(I15:I22) -> -117505.49 | ... AK23: =SUM(AK15:AK22) -> -185553.19
A25: EBITDA | B25: =B12+B23 -> -71152.144 | C25: =C12+C23 -> -67510.26 | D25: =D12+D23 -> -63451.917 | E25: =E12+E23 -> -58929.492 | F25: =F12+F23 -> -53889.916 | G25: =G12+G23 -> -48274.052 | H25: =H12+H23 -> -42015.999 | I25: =I12+I23 -> -35042.322 | ... AK25: =AK12+AK23 -> 161246.81
A26: Cumulative EBITDA less capex | B26: =B25-Assumptions!$B$41 -> -711152.14 | C26: =B26+C25 -> -778662.4 | D26: =C26+D25 -> -842114.32 | E26: =D26+E25 -> -901043.81 | F26: =E26+F25 -> -954933.73 | G26: =F26+G25 -> -1003207.8 | H26: =G26+H25 -> -1045223.8 | I26: =H26+I25 -> -1080266.1 | J26: =I26+J25 -> -1107537.3 | ... AK26: =AJ26+AK25 -> 714825.88

Sheet Annual Summary
A1: GYM & FITNESS STUDIO | ANNUAL SUMMARY
A2: 3-year P&L, revenue mix, member metrics and funding requirement.
A4: 3-YEAR P&L SUMMARY
A5: Line Item | B5: FY1 | C5: FY2 | D5: FY3 | E5: 3-Yr Total | F5: % of 3-Yr Rev
A6: Standard membership revenue | B6: =SUM('Monthly P&L'!B8:M8) -> 381999.47 | C6: =SUM('Monthly P&L'!N8:Y8) -> 934053.92 | D6: =SUM('Monthly P&L'!Z8:AK8) -> 1505863.1 | E6: =SUM(B6:D6) -> 2821916.5 | F6: =E6/$E$10 -> 0.42387543
A7: Premium membership revenue | B7: =SUM('Monthly P&L'!B9:M9) -> 257264.95 | C7: =SUM('Monthly P&L'!N9:Y9) -> 629056.72 | D7: =SUM('Monthly P&L'!Z9:AK9) -> 1014152.7 | E7: =SUM(B7:D7) -> 1900474.4 | F7: =E7/$E$10 -> 0.28546713
A8: Personal training revenue | B8: =SUM('Monthly P&L'!B10:M10) -> 224522.13 | C8: =SUM('Monthly P&L'!N10:Y10) -> 548994.96 | D8: =SUM('Monthly P&L'!Z10:AK10) -> 885078.73 | E8: =SUM(B8:D8) -> 1658595.8 | F8: =E8/$E$10 -> 0.24913495
A9: Class pack revenue | B9: =SUM('Monthly P&L'!B11:M11) -> 37420.356 | C9: =SUM('Monthly P&L'!N11:Y11) -> 91499.159 | D9: =SUM('Monthly P&L'!Z11:AK11) -> 147513.12 | E9: =SUM(B9:D9) -> 276432.64 | F9: =E9/$E$10 -> 0.041522491
A10: TOTAL REVENUE | B10: =SUM('Monthly P&L'!B12:M12) -> 901206.9 | C10: =SUM('Monthly P&L'!N12:Y12) -> 2203604.8 | D10: =SUM('Monthly P&L'!Z12:AK12) -> 3552607.7 | E10: =SUM(B10:D10) -> 6657419.3
A11: Total costs | B11: =SUM('Monthly P&L'!B23:M23) -> -1394524.7 | C11: =SUM('Monthly P&L'!N23:Y23) -> -1770203.5 | D11: =SUM('Monthly P&L'!Z23:AK23) -> -2137865.2 | E11: =SUM(B11:D11) -> -5302593.5
A12: EBITDA | B12: =SUM('Monthly P&L'!B25:M25) -> -493317.83 | C12: =SUM('Monthly P&L'!N25:Y25) -> 433401.21 | D12: =SUM('Monthly P&L'!Z25:AK25) -> 1414742.5 | E12: =SUM(B12:D12) -> 1354825.9
A13: EBITDA margin % | B13: =B12/B10 -> -0.54739686 | C13: =C12/C10 -> 0.19667829 | D13: =D12/D10 -> 0.39822649
A15: MEMBER METRICS (end-of-year)
A16: Members (Dec closing) | B16: ='Member Build'!M10 -> 220 | C16: ='Member Build'!Y10 -> 420 | D16: ='Member Build'!AK10 -> 600
A17: Monthly revenue per member (Dec) | B17: ='Monthly P&L'!M12/'Member Build'!M10 -> 578 | C17: ='Monthly P&L'!Y12/'Member Build'!Y10 -> 578 | D17: ='Monthly P&L'!AK12/'Member Build'!AK10 -> 578
A19: FUNDING REQUIREMENT
A20: One-Time Capex | B20: =Assumptions!B41 -> 640000
A21: Peak cumulative cash shortfall (incl. capex) | B21: =-MIN('Monthly P&L'!B26:AK26) -> 1138958
A22: Implied Funding Required | B22: =B21 -> 1138958
A23: Break-even month (cumulative cash turns positive) | B23: =MATCH(TRUE(),'Monthly P&L'!B26:AK26>0,0) -> 32 | E23: Array formula — month index where cumulative EBITDA less capex first exceeds zero.
