Workbook

Sheet Cover
B2: HOME SERVICES APP — 3-YEAR FINANCIAL MODEL
B3: On-Demand Home Services App · Qatar · Base Case Build, 2026
B5: OVERVIEW
B6: Bottom-up 3-year financial model for the app in Qatar. Starts from the Qatar market funnel (TAM → SAM → Downloads → Active Customers) and builds through to a monthly P&L and EBITDA. Yellow-highlighted cells are analyst estimates — adjust them to stress-test the model.
B8: NAVIGATE THE MODEL
B9: 1 · Assumptions | C9: All inputs — Qatar market data, subscription pricing, funnel rates, growth targets, cost estimates. Yellow cells are analyst estimates; change these to run scenarios.
B10: 2 · Volume & Funnel Build | C10: Monthly drivers for 36 months — app downloads, active customers, in-house vs. marketplace job split, subscriber counts by tier.
B11: 3 · Monthly P&L | C11: Four revenue streams (in-house jobs, marketplace commission, booking fees, subscriptions), margins to EBITDA — monthly detail plus FY1–3 annual totals.
B12: 4 · Annual Summary | C12: 3-year P&L rollup, revenue mix by stream, implied funding requirement, and graduation metrics vs. Phase 1 targets.
B14: COLOUR LEGEND
B15: Blue | C15: Given input — Qatar market data or app rate card
B16: Blue + yellow | C16: Analyst estimate — independently derived; adjust to stress-test
B17: Black | C17: Formula / calculation — do not overwrite
B18: Green | C18: Link pulling from another tab — do not overwrite

Sheet Assumptions
A1: HOME SERVICES APP — MODEL ASSUMPTIONS
A2: Blue = given (market data / app rate card). Yellow = your estimate — change to stress-test. Black = formula, do not edit.
A4: MARKET CONTEXT — QATAR
A5: Qatar Population (2026) | B5: 3170000 | E5: Qatar resident population, 2026 estimate.
A6: Total Residential Units | B6: 399542 | E6: Estimated total residential housing stock, Qatar, 2026.
A7: Family Households — total universe | B7: 220000 | E7: Households vs. single-occupant/shared units, Qatar.
A8: Self-Managed Households (B2C target) | B8: 165000 | E8: Households managing their own maintenance — not via a building FM contract.
A9: App-Ready Household Rate (SAM % of Family HH) | B9: 0.35 | E9: What share of family households will book via a mobile app rather than a personal contractor or WhatsApp referral?
A10: SAM — App-Ready Households | B10: =B7*B9 -> 77000 | E10: Family Households × App-Ready Rate
A12: DOWNLOAD & ACTIVATION FUNNEL | B12: Y1 | C12: Y2 | D12: Y3
A13: Cumulative App Downloads — Month 1 seed | B13: 500 | E13: Controlled soft-launch cohort at Month 1, before wider marketing spend begins.
A14: What % of SAM do we want to acquire by year end? | B14: 0.01 | C14: 0.18 | D14: 0.3 | E14: Target cumulative download penetration of SAM at end of each year. [Y1 | Y2 | Y3]
A15: Implied download target (#) — derived | B15: =B10*B14 -> 770 | C15: =B10*C14 -> 13860 | D15: =B10*D14 -> 23100 | E15: SAM × target penetration rate.
A17: Implied monthly download growth rate — derived | B17: =(B15/B13)^(1/11)-1 -> 0.040033524 | C17: =(C15/B15)^(1/11)-1 -> 0.30051595 | D17: =(D15/C15)^(1/11)-1 -> 0.047533856 | E17: Monthly compounding rate needed to hit each year-end download target. [Y1 | Y2 | Y3]
A19: Activation rate — downloads → active customers | B19: 0.15 | C19: 0.18 | D19: 0.2 | E19: What cumulative % of app downloads place a booking? [Y1 | Y2 | Y3]
A20: Avg monthly bookings per active customer | B20: 0.27 | E20: How often does an active customer re-book per month? (~1 job every 3–4 months)
A21: In-house job share vs third-party | B21: 0.75 | C21: 0.6 | D21: 0.5 | E21: What % of total jobs go to our in-house team? Phase 1: in-house first. Phase 3: even split. [Y1 | Y2 | Y3]
A23: SUBSCRIBER GROWTH — CONVERSION-RATE DRIVEN | B23: Y1 | C23: Y2 | D23: Y3
A24: Cleaning subs — Month 1 seed | B24: 5 | E24: Early-adopter cohort at launch.
A25: What % of active customers convert to a cleaning sub? | B25: 0.1 | C25: 0.12 | D25: 0.13 | E25: Natural upsell from a one-off booking. Conversion improves as brand trust matures. [Y1 | Y2 | Y3]
A26: Cleaning subs — year-end target (#) — derived | B26: ='Volume & Funnel Build'!$M$11*B25 -> 11.55 | C26: ='Volume & Funnel Build'!$Y$11*C25 -> 299.376 | D26: ='Volume & Funnel Build'!$AK$11*D25 -> 600.6 | E26: Active Customers (Dec) × Cleaning Conversion Rate. [Y1 | Y2 | Y3]
A27: Implied monthly growth — cleaning subs — derived | B27: =(B26/B24)^(1/11)-1 -> 0.079084948 | C27: =(C26/B26)^(1/11)-1 -> 0.34434976 | D27: =(D26/C26)^(1/11)-1 -> 0.065339504 | E27: Monthly compounding growth to hit each year-end cleaning subscriber target. [Y1 | Y2 | Y3]
A29: PM Plan subs — Month 1 seed | B29: 5 | E29: Early-adopter cohort at launch.
A30: What % of active customers convert to a PM plan? | B30: 0.06 | C30: 0.07 | D30: 0.085 | E30: Higher-commitment annual product — lower attach rate than cleaning subs. [Y1 | Y2 | Y3]
A31: PM Plan subs — year-end target (#) — derived | B31: ='Volume & Funnel Build'!$M$11*B30 -> 6.93 | C31: ='Volume & Funnel Build'!$Y$11*C30 -> 174.636 | D31: ='Volume & Funnel Build'!$AK$11*D30 -> 392.7 | E31: Active Customers (Dec) × PM Plan Conversion Rate. [Y1 | Y2 | Y3]
A32: Implied monthly growth — PM subs — derived | B32: =(B31/B29)^(1/11)-1 -> 0.0301194 | C32: =(C31/B31)^(1/11)-1 -> 0.3409113 | D32: =(D31/C31)^(1/11)-1 -> 0.076448793 | E32: Monthly compounding growth to hit each year-end PM subscriber target. [Y1 | Y2 | Y3]
A34: PRICING & UNIT ECONOMICS | B34: Y1 | C34: Y2 | D34: Y3
A35: Blended average order value — AOV (QAR) | B35: 220 | E35: What is the average job value we charge? Blended across AC, electrical, plumbing, pest control.
A36: Marketplace commission rate | B36: 0.22 | E36: What % commission do we take from third-party techs?
A37: Booking fee per booking (QAR) | B37: 0 | E37: (optional) Small platform convenience fee charged on every booking.
A38: Emergency premium multiplier | B38: 0 | E38: (optional) Same-day / after-hours jobs charged at this multiple of the standard price.
A39: Emergency jobs as % of total jobs | B39: 0.011 | E39: (optional) What % of total jobs are urgent / same-day emergency requests?
A40: In-house job margin | B40: 0.65 | E40: What margin do we make on in-house jobs? After tech wages and materials.
A41: Marketplace commission margin | B41: 0.95 | E41: Near-zero delivery cost — the third-party tech bears the job cost.
A42: Booking fee margin | B42: 1 | E42: Pure platform fee, no direct cost.
A43: Emergency premium margin | B43: =B40 -> 0.65 | E43: Assumed equal to in-house job margin — emergency jobs go to the in-house team first.
A44: Cleaning subscription margin | B44: 0.58 | E44: What margin do we make on cleaning subs? After staff labour and consumables.
A45: PM Plan margin | B45: 0.6 | E45: What margin do we make on PM plan subs? After scheduled visit labour and parts.
A47: SUBSCRIPTION PRICING & TIER MIX | B47: Y1 | C47: Y2 | D47: Y3
A48: Cleaning — Basic price (QAR/mo) | B48: 350 | E48: App rate card — ~4 cleaning sessions/month.
A49: Cleaning — Essential price (QAR/mo) | B49: 680 | E49: App rate card — ~8 cleaning sessions/month.
A50: Cleaning — Premium price (QAR/mo) | B50: 1000 | E50: App rate card — ~12 cleaning sessions/month.
A51: Cleaning — Basic tier mix % | B51: 0.5 | E51: What % of cleaning subscribers choose Basic? Most subscribers start at the entry tier.
A52: Cleaning — Essential tier mix % | B52: 0.35
A53: Cleaning — Premium tier mix % | B53: 0.15 | E53: Premium (3×/week) appeals to a smaller, higher-income slice.
A55: PM Plan — Bronze price (QAR/mo) | B55: 89 | E55: Entry AMC tier — one annual AC + electrical + plumbing check-up.
A56: PM Plan — Silver price (QAR/mo) | B56: 149 | E56: Mid tier — adds a mid-year visit and minor-parts discount.
A57: PM Plan — Gold price (QAR/mo) | B57: 249 | E57: Premium tier — quarterly visits plus priority same-day response.
A58: PM Plan — Bronze tier mix % | B58: 0.5 | E58: Entry tier captures the majority of AMC sign-ups.
A59: PM Plan — Silver tier mix % | B59: 0.35
A60: PM Plan — Gold tier mix % | B60: 0.15
A62: Monthly subscriber churn rate | B62: 0.04 | E62: What % of subscribers cancel each month? (~4%/month ≈ 38% annual churn)
A65: OPERATING COST ASSUMPTIONS | B65: Y1 | C65: Y2 | D65: Y3
A66: Marketing cost per new app download — CPI (QAR) | B66: 8 | E66: How much do we spend to acquire each new download? Marketing Opex = net new downloads × CPI.
A67: Staff costs — annual (QAR) | B67: 0 | C67: 0 | D67: 0 | E67: In-house tech team, call centre, team leaders, management allocation. Replace with HR actuals. [Y1 | Y2 | Y3]
A68: Platform & tech costs — annual (QAR) | B68: 10000 | C68: 10000 | D68: 10000 | E68: App hosting, maintenance, third-party integrations. [Y1 | Y2 | Y3]
A69: Admin & G&A — annual (QAR) | B69: 60000 | C69: 60000 | D69: 60000 | E69: Office, legal/compliance, insurance, admin overhead. [Y1 | Y2 | Y3]
A71: ONE-TIME CAPEX | B71: Y1 | C71: Y2 | D71: Y3
A72: App finalisation & QA | B72: 0
A73: Call centre / tech systems setup | B73: 0
A74: In-house tech tooling & equipment | B74: 0
A75: Pre-launch marketing campaign | B75: 5000
A76: Office / warehouse setup | B76: 0
A77: Total One-Time Capex | B77: =SUM(B72:B76) -> 5000

Sheet Volume & Funnel Build
A1: VOLUME & FUNNEL BUILD
A2: TAM 399,542 units → 220,000 family households → SAM (Assumptions) → App Downloads (ramped) → Active Customers → Jobs/month → Subscribers. All figures in units (#) unless noted.
B4: YEAR 1 (2026) | N4: YEAR 2 (2027) | Z4: YEAR 3 (2028) | AL4: FY1 | AM4: FY2 | AN4: FY3
B5: 46048 | C5: 46079 | D5: 46107 | E5: 46138 | F5: 46168 | G5: 46199 | H5: 46229 | I5: 46260 | J5: 46291 | K5: 46321 | L5: 46352 | M5: 46382 | N5: 46049 | O5: 46080 | P5: 46108 | Q5: 46139 | R5: 46169 | S5: 46200 | T5: 46230 | U5: 46261 | V5: 46292 | W5: 46322 | X5: 46353 | Y5: 46383 | Z5: 46050 | AA5: 46081 | AB5: 46109 | AC5: 46140 | AD5: 46170 | AE5: 46201 | AF5: 46231 | AG5: 46262 | AH5: 46293 | AI5: 46323 | AJ5: 46354 | AK5: 46384 | AL5: FY1 Total | AM5: FY2 Total | AN5: FY3 Total
A7: Cumulative App Downloads (#) | B7: =Assumptions!B13 -> 500 | C7: =B7*(1+Assumptions!B17) -> 520.01676 | D7: =C7*(1+Assumptions!B17) -> 540.83487 | E7: =D7*(1+Assumptions!B17) -> 562.48639 | F7: =E7*(1+Assumptions!B17) -> 585.0047 | G7: =F7*(1+Assumptions!B17) -> 608.4245 | H7: =G7*(1+Assumptions!B17) -> 632.78188 | I7: =H7*(1+Assumptions!B17) -> 658.11437 | J7: =I7*(1+Assumptions!B17) -> 684.461 | K7: =J7*(1+Assumptions!B17) -> 711.86239 | L7: =K7*(1+Assumptions!B17) -> 740.36075 | M7: =L7*(1+Assumptions!B17) -> 770 | N7: =M7 -> 770 | O7: =N7*(1+Assumptions!C17) -> 1001.3973 | P7: =O7*(1+Assumptions!C17) -> 1302.3331 | Q7: =P7*(1+Assumptions!C17) -> 1693.705 | R7: =Q7*(1+Assumptions!C17) -> 2202.6904 | S7: =R7*(1+Assumptions!C17) -> 2864.634 | T7: =S7*(1+Assumptions!C17) -> 3725.5022 | U7: =T7*(1+Assumptions!C17) -> 4845.075 | V7: =U7*(1+Assumptions!C17) -> 6301.0973 | W7: =V7*(1+Assumptions!C17) -> 8194.6775 | X7: =W7*(1+Assumptions!C17) -> 10657.309 | Y7: =X7*(1+Assumptions!C17) -> 13860 | Z7: =Y7 -> 13860 | AA7: =Z7*(1+Assumptions!D17) -> 14518.819 | AB7: =AA7*(1+Assumptions!D17) -> 15208.955 | AC7: =AB7*(1+Assumptions!D17) -> 15931.895 | AD7: =AC7*(1+Assumptions!D17) -> 16689.199 | AE7: =AD7*(1+Assumptions!D17) -> 17482.501 | AF7: =AE7*(1+Assumptions!D17) -> 18313.512 | AG7: =AF7*(1+Assumptions!D17) -> 19184.024 | AH7: =AG7*(1+Assumptions!D17) -> 20095.915 | AI7: =AH7*(1+Assumptions!D17) -> 21051.151 | AJ7: =AI7*(1+Assumptions!D17) -> 22051.793 | AK7: =AJ7*(1+Assumptions!D17) -> 23100 | AL7: =M7 -> 770 | AM7: =Y7 -> 13860 | AN7: =AK7 -> 23100
A8: Net New Downloads (#) | B8: =B7 -> 500 | C8: =C7-B7 -> 20.016762 | D8: =D7-C7 -> 20.818103 | E8: =E7-D7 -> 21.651525 | F8: =F7-E7 -> 22.518312 | G8: =G7-F7 -> 23.4198 | H8: =H7-G7 -> 24.357377 | I8: =I7-H7 -> 25.332488 | J8: =J7-I7 -> 26.346637 | ... AK8: =AK7-AJ7 -> 1048.2068 | AL8: =SUM(B8:M8) -> 770 | AM8: =SUM(N8:Y8) -> 13090 | AN8: =SUM(Z8:AK8) -> 9240
A9: Market Penetration - Downloads(% of SAM) | B9: =B7/Assumptions!B10 -> 0.0064935065 | C9: =C7/Assumptions!B10 -> 0.0067534644 | D9: =D7/Assumptions!B10 -> 0.0070238294 | E9: =E7/Assumptions!B10 -> 0.0073050181 | F9: =F7/Assumptions!B10 -> 0.0075974637 | G9: =G7/Assumptions!B10 -> 0.0079016169 | H9: =H7/Assumptions!B10 -> 0.0082179465 | I9: =I7/Assumptions!B10 -> 0.0085469398 | J9: =J7/Assumptions!B10 -> 0.008889104 | K9: =K7/Assumptions!B10 -> 0.0092449661 | L9: =L7/Assumptions!B10 -> 0.0096150747 | M9: =M7/Assumptions!B10 -> 0.01 | N9: =N7/Assumptions!B10 -> 0.01 | O9: =O7/Assumptions!B10 -> 0.013005159 | P9: =P7/Assumptions!B10 -> 0.016913417 | Q9: =Q7/Assumptions!B10 -> 0.021996169 | R9: =R7/Assumptions!B10 -> 0.028606369 | S9: =S7/Assumptions!B10 -> 0.037203038 | T9: =T7/Assumptions!B10 -> 0.048383145 | U9: =U7/Assumptions!B10 -> 0.062923052 | V9: =V7/Assumptions!B10 -> 0.081832432 | W9: =W7/Assumptions!B10 -> 0.10642438 | X9: =X7/Assumptions!B10 -> 0.13840661 | Y9: =Y7/Assumptions!B10 -> 0.18 | Z9: =Z7/Assumptions!B10 -> 0.18 | AA9: =AA7/Assumptions!B10 -> 0.18855609 | AB9: =AB7/Assumptions!B10 -> 0.19751889 | AC9: =AC7/Assumptions!B10 -> 0.20690773 | AD9: =AD7/Assumptions!B10 -> 0.21674285 | AE9: =AE7/Assumptions!B10 -> 0.22704547 | AF9: =AF7/Assumptions!B10 -> 0.23783782 | AG9: =AG7/Assumptions!B10 -> 0.24914317 | AH9: =AH7/Assumptions!B10 -> 0.2609859 | AI9: =AI7/Assumptions!B10 -> 0.27339157 | AJ9: =AJ7/Assumptions!B10 -> 0.28638693 | AK9: =AK7/Assumptions!B10 -> 0.3 | AL9: =M9 -> 0.01 | AM9: =Y9 -> 0.18 | AN9: =AK9 -> 0.3
A11: Active Customers (#) | B11: =B7*Assumptions!B19 -> 75 | C11: =C7*Assumptions!B19 -> 78.002514 | D11: =D7*Assumptions!B19 -> 81.12523 | E11: =E7*Assumptions!B19 -> 84.372959 | F11: =F7*Assumptions!B19 -> 87.750705 | G11: =G7*Assumptions!B19 -> 91.263675 | H11: =H7*Assumptions!B19 -> 94.917282 | I11: =I7*Assumptions!B19 -> 98.717155 | J11: =J7*Assumptions!B19 -> 102.66915 | K11: =K7*Assumptions!B19 -> 106.77936 | L11: =L7*Assumptions!B19 -> 111.05411 | M11: =M7*Assumptions!B19 -> 115.5 | N11: =N7*Assumptions!C19 -> 138.6 | O11: =O7*Assumptions!C19 -> 180.25151 | P11: =P7*Assumptions!C19 -> 234.41996 | Q11: =Q7*Assumptions!C19 -> 304.8669 | R11: =R7*Assumptions!C19 -> 396.48427 | S11: =S7*Assumptions!C19 -> 515.63411 | T11: =T7*Assumptions!C19 -> 670.59039 | U11: =U7*Assumptions!C19 -> 872.11349 | V11: =V7*Assumptions!C19 -> 1134.1975 | W11: =W7*Assumptions!C19 -> 1475.0419 | X11: =X7*Assumptions!C19 -> 1918.3156 | Y11: =Y7*Assumptions!C19 -> 2494.8 | Z11: =Z7*Assumptions!D19 -> 2772 | AA11: =AA7*Assumptions!D19 -> 2903.7638 | AB11: =AB7*Assumptions!D19 -> 3041.7909 | AC11: =AC7*Assumptions!D19 -> 3186.379 | AD11: =AD7*Assumptions!D19 -> 3337.8399 | AE11: =AE7*Assumptions!D19 -> 3496.5003 | AF11: =AF7*Assumptions!D19 -> 3662.7024 | AG11: =AG7*Assumptions!D19 -> 3836.8048 | AH11: =AH7*Assumptions!D19 -> 4019.1829 | AI11: =AI7*Assumptions!D19 -> 4210.2302 | AJ11: =AJ7*Assumptions!D19 -> 4410.3586 | AK11: =AK7*Assumptions!D19 -> 4620 | AL11: =M11 -> 115.5 | AM11: =Y11 -> 2494.8 | AN11: =AK11 -> 4620
A13: Total Jobs / Month (#) | B13: =B11*Assumptions!B20 -> 20.25 | C13: =C11*Assumptions!B20 -> 21.060679 | D13: =D11*Assumptions!B20 -> 21.903812 | E13: =E11*Assumptions!B20 -> 22.780699 | F13: =F11*Assumptions!B20 -> 23.69269 | G13: =G11*Assumptions!B20 -> 24.641192 | H13: =H11*Assumptions!B20 -> 25.627666 | I13: =I11*Assumptions!B20 -> 26.653632 | J13: =J11*Assumptions!B20 -> 27.720671 | K13: =K11*Assumptions!B20 -> 28.830427 | L13: =L11*Assumptions!B20 -> 29.98461 | M13: =M11*Assumptions!B20 -> 31.185 | N13: =N11*Assumptions!B20 -> 37.422 | O13: =O11*Assumptions!B20 -> 48.667908 | P13: =P11*Assumptions!B20 -> 63.29339 | Q13: =Q11*Assumptions!B20 -> 82.314063 | R13: =R11*Assumptions!B20 -> 107.05075 | S13: =S11*Assumptions!B20 -> 139.22121 | T13: =T11*Assumptions!B20 -> 181.0594 | U13: =U11*Assumptions!B20 -> 235.47064 | V13: =V11*Assumptions!B20 -> 306.23333 | W13: =W11*Assumptions!B20 -> 398.26133 | X13: =X11*Assumptions!B20 -> 517.94521 | Y13: =Y11*Assumptions!B20 -> 673.596 | Z13: =Z11*Assumptions!B20 -> 748.44 | AA13: =AA11*Assumptions!B20 -> 784.01624 | AB13: =AB11*Assumptions!B20 -> 821.28355 | AC13: =AC11*Assumptions!B20 -> 860.32233 | AD13: =AD11*Assumptions!B20 -> 901.21677 | AE13: =AE11*Assumptions!B20 -> 944.05507 | AF13: =AF11*Assumptions!B20 -> 988.92965 | AG13: =AG11*Assumptions!B20 -> 1035.9373 | AH13: =AH11*Assumptions!B20 -> 1085.1794 | AI13: =AI11*Assumptions!B20 -> 1136.7621 | AJ13: =AJ11*Assumptions!B20 -> 1190.7968 | AK13: =AK11*Assumptions!B20 -> 1247.4 | AL13: =SUM(B13:M13) -> 304.33108 | AM13: =SUM(N13:Y13) -> 2790.5352 | AN13: =SUM(Z13:AK13) -> 11744.339
A14: In-House Jobs (#) | B14: =B13*Assumptions!B21 -> 15.1875 | C14: =C13*Assumptions!B21 -> 15.795509 | D14: =D13*Assumptions!B21 -> 16.427859 | E14: =E13*Assumptions!B21 -> 17.085524 | F14: =F13*Assumptions!B21 -> 17.769518 | G14: =G13*Assumptions!B21 -> 18.480894 | H14: =H13*Assumptions!B21 -> 19.22075 | I14: =I13*Assumptions!B21 -> 19.990224 | J14: =J13*Assumptions!B21 -> 20.790503 | K14: =K13*Assumptions!B21 -> 21.62282 | L14: =L13*Assumptions!B21 -> 22.488458 | M14: =M13*Assumptions!B21 -> 23.38875 | N14: =N13*Assumptions!C21 -> 22.4532 | O14: =O13*Assumptions!C21 -> 29.200745 | P14: =P13*Assumptions!C21 -> 37.976034 | Q14: =Q13*Assumptions!C21 -> 49.388438 | R14: =R13*Assumptions!C21 -> 64.230451 | S14: =S13*Assumptions!C21 -> 83.532726 | T14: =T13*Assumptions!C21 -> 108.63564 | U14: =U13*Assumptions!C21 -> 141.28239 | V14: =V13*Assumptions!C21 -> 183.74 | W14: =W13*Assumptions!C21 -> 238.9568 | X14: =X13*Assumptions!C21 -> 310.76712 | Y14: =Y13*Assumptions!C21 -> 404.1576 | Z14: =Z13*Assumptions!D21 -> 374.22 | AA14: =AA13*Assumptions!D21 -> 392.00812 | AB14: =AB13*Assumptions!D21 -> 410.64178 | AC14: =AC13*Assumptions!D21 -> 430.16116 | AD14: =AD13*Assumptions!D21 -> 450.60838 | AE14: =AE13*Assumptions!D21 -> 472.02754 | AF14: =AF13*Assumptions!D21 -> 494.46483 | AG14: =AG13*Assumptions!D21 -> 517.96865 | AH14: =AH13*Assumptions!D21 -> 542.58969 | AI14: =AI13*Assumptions!D21 -> 568.38107 | AJ14: =AJ13*Assumptions!D21 -> 595.39842 | AK14: =AK13*Assumptions!D21 -> 623.7 | AL14: =SUM(B14:M14) -> 228.24831 | AM14: =SUM(N14:Y14) -> 1674.3211 | AN14: =SUM(Z14:AK14) -> 5872.1696
A15: Third-Party Jobs (#) | B15: =B13-B14 -> 5.0625 | C15: =C13-C14 -> 5.2651697 | D15: =D13-D14 -> 5.475953 | E15: =E13-E14 -> 5.6951747 | F15: =F13-F14 -> 5.9231726 | G15: =G13-G14 -> 6.1602981 | H15: =H13-H14 -> 6.4069165 | I15: =I13-I14 -> 6.663408 | ... AK15: =AK13-AK14 -> 623.7 | AL15: =SUM(B15:M15) -> 76.08277 | AM15: =SUM(N15:Y15) -> 1116.2141 | AN15: =SUM(Z15:AK15) -> 5872.1696
A17: Cleaning Subscribers — Total (#) | B17: =Assumptions!B24 -> 5 | C17: =B17*(1+Assumptions!B27) -> 5.3954247 | D17: =C17*(1+Assumptions!B27) -> 5.8221216 | E17: =D17*(1+Assumptions!B27) -> 6.2825638 | F17: =E17*(1+Assumptions!B27) -> 6.77942 | G17: =F17*(1+Assumptions!B27) -> 7.3155701 | H17: =G17*(1+Assumptions!B27) -> 7.8941216 | I17: =H17*(1+Assumptions!B27) -> 8.5184278 | J17: =I17*(1+Assumptions!B27) -> 9.1921072 | K17: =J17*(1+Assumptions!B27) -> 9.9190645 | L17: =K17*(1+Assumptions!B27) -> 10.703513 | M17: =L17*(1+Assumptions!B27) -> 11.55 | N17: =M17 -> 11.55 | O17: =N17*(1+Assumptions!C27) -> 15.52724 | P17: =O17*(1+Assumptions!C27) -> 20.874041 | Q17: =P17*(1+Assumptions!C27) -> 28.062012 | R17: =Q17*(1+Assumptions!C27) -> 37.725159 | S17: =R17*(1+Assumptions!C27) -> 50.715808 | T17: =S17*(1+Assumptions!C27) -> 68.179784 | U17: =T17*(1+Assumptions!C27) -> 91.657476 | V17: =U17*(1+Assumptions!C27) -> 123.2197 | W17: =V17*(1+Assumptions!C27) -> 165.65038 | X17: =W17*(1+Assumptions!C27) -> 222.69205 | Y17: =X17*(1+Assumptions!C27) -> 299.376 | Z17: =Y17 -> 299.376 | AA17: =Z17*(1+Assumptions!D27) -> 318.93708 | AB17: =AA17*(1+Assumptions!D27) -> 339.77627 | AC17: =AB17*(1+Assumptions!D27) -> 361.97708 | AD17: =AC17*(1+Assumptions!D27) -> 385.62849 | AE17: =AD17*(1+Assumptions!D27) -> 410.82526 | AF17: =AE17*(1+Assumptions!D27) -> 437.66838 | AG17: =AF17*(1+Assumptions!D27) -> 466.26541 | AH17: =AG17*(1+Assumptions!D27) -> 496.73096 | AI17: =AH17*(1+Assumptions!D27) -> 529.18712 | AJ17: =AI17*(1+Assumptions!D27) -> 563.76394 | AK17: =AJ17*(1+Assumptions!D27) -> 600.6 | AL17: =M17 -> 11.55 | AM17: =Y17 -> 299.376 | AN17: =AK17 -> 600.6
A18: Gross New Cleaning Subs (churn-adj.) (#) | B18: =B17 -> 5 | C18: =C17-B17*(1-Assumptions!B62) -> 0.59542474 | D18: =D17-C17*(1-Assumptions!B62) -> 0.64251387 | E18: =E17-D17*(1-Assumptions!B62) -> 0.69332705 | F18: =F17-E17*(1-Assumptions!B62) -> 0.74815878 | G18: =G17-F17*(1-Assumptions!B62) -> 0.80732688 | H18: =H17-G17*(1-Assumptions!B62) -> 0.87117428 | I18: =I17-H17*(1-Assumptions!B62) -> 0.94007106 | J18: =J17-I17*(1-Assumptions!B62) -> 1.0144165 | K18: =K17-J17*(1-Assumptions!B62) -> 1.0946416 | L18: =L17-K17*(1-Assumptions!B62) -> 1.1812113 | M18: =M17-L17*(1-Assumptions!B62) -> 1.2746273 | N18: =N17-M17*(1-Assumptions!B62) -> 0.462 | O18: =O17-N17*(1-Assumptions!B62) -> 4.4392397 | P18: =P17-O17*(1-Assumptions!B62) -> 5.9678908 | Q18: =Q17-P17*(1-Assumptions!B62) -> 8.0229325 | R18: =R17-Q17*(1-Assumptions!B62) -> 10.785627 | S18: =S17-R17*(1-Assumptions!B62) -> 14.499655 | T18: =T17-S17*(1-Assumptions!B62) -> 19.492608 | U18: =U17-T17*(1-Assumptions!B62) -> 26.204883 | V18: =V17-U17*(1-Assumptions!B62) -> 35.228528 | W18: =W17-V17*(1-Assumptions!B62) -> 47.359463 | X18: =X17-W17*(1-Assumptions!B62) -> 63.667683 | Y18: =Y17-X17*(1-Assumptions!B62) -> 85.591634 | Z18: =Z17-Y17*(1-Assumptions!B62) -> 11.97504 | AA18: =AA17-Z17*(1-Assumptions!B62) -> 31.536119 | AB18: =AB17-AA17*(1-Assumptions!B62) -> 33.596674 | AC18: =AC17-AB17*(1-Assumptions!B62) -> 35.791864 | AD18: =AD17-AC17*(1-Assumptions!B62) -> 38.130486 | AE18: =AE17-AD17*(1-Assumptions!B62) -> 40.621913 | AF18: =AF17-AE17*(1-Assumptions!B62) -> 43.276129 | AG18: =AG17-AF17*(1-Assumptions!B62) -> 46.10377 | AH18: =AH17-AG17*(1-Assumptions!B62) -> 49.116167 | AI18: =AI17-AH17*(1-Assumptions!B62) -> 52.325393 | AJ18: =AJ17-AI17*(1-Assumptions!B62) -> 55.744309 | AK18: =AK17-AJ17*(1-Assumptions!B62) -> 59.386614 | AL18: =SUM(B18:M18) -> 14.862893 | AM18: =SUM(N18:Y18) -> 321.72215 | AN18: =SUM(Z18:AK18) -> 497.60448
A19: Cleaning — Basic (#) | B19: =B17*Assumptions!B51 -> 2.5 | C19: =C17*Assumptions!B51 -> 2.6977124 | D19: =D17*Assumptions!B51 -> 2.9110608 | E19: =E17*Assumptions!B51 -> 3.1412819 | F19: =F17*Assumptions!B51 -> 3.38971 | G19: =G17*Assumptions!B51 -> 3.6577851 | H19: =H17*Assumptions!B51 -> 3.9470608 | I19: =I17*Assumptions!B51 -> 4.2592139 | J19: =J17*Assumptions!B51 -> 4.5960536 | K19: =K17*Assumptions!B51 -> 4.9595323 | L19: =L17*Assumptions!B51 -> 5.3517566 | M19: =M17*Assumptions!B51 -> 5.775 | N19: =N17*Assumptions!B51 -> 5.775 | O19: =O17*Assumptions!B51 -> 7.7636198 | P19: =P17*Assumptions!B51 -> 10.43702 | Q19: =Q17*Assumptions!B51 -> 14.031006 | R19: =R17*Assumptions!B51 -> 18.862579 | S19: =S17*Assumptions!B51 -> 25.357904 | T19: =T17*Assumptions!B51 -> 34.089892 | U19: =U17*Assumptions!B51 -> 45.828738 | V19: =V17*Assumptions!B51 -> 61.609852 | W19: =W17*Assumptions!B51 -> 82.82519 | X19: =X17*Assumptions!B51 -> 111.34602 | Y19: =Y17*Assumptions!B51 -> 149.688 | Z19: =Z17*Assumptions!B51 -> 149.688 | AA19: =AA17*Assumptions!B51 -> 159.46854 | AB19: =AB17*Assumptions!B51 -> 169.88813 | AC19: =AC17*Assumptions!B51 -> 180.98854 | AD19: =AD17*Assumptions!B51 -> 192.81424 | AE19: =AE17*Assumptions!B51 -> 205.41263 | AF19: =AF17*Assumptions!B51 -> 218.83419 | AG19: =AG17*Assumptions!B51 -> 233.13271 | AH19: =AH17*Assumptions!B51 -> 248.36548 | AI19: =AI17*Assumptions!B51 -> 264.59356 | AJ19: =AJ17*Assumptions!B51 -> 281.88197 | AK19: =AK17*Assumptions!B51 -> 300.3 | AL19: =M19 -> 5.775 | AM19: =Y19 -> 149.688 | AN19: =AK19 -> 300.3
A20: Cleaning — Essential (#) | B20: =B17*Assumptions!B52 -> 1.75 | C20: =C17*Assumptions!B52 -> 1.8883987 | D20: =D17*Assumptions!B52 -> 2.0377426 | E20: =E17*Assumptions!B52 -> 2.1988973 | F20: =F17*Assumptions!B52 -> 2.372797 | G20: =G17*Assumptions!B52 -> 2.5604495 | H20: =H17*Assumptions!B52 -> 2.7629426 | I20: =I17*Assumptions!B52 -> 2.9814497 | J20: =J17*Assumptions!B52 -> 3.2172375 | K20: =K17*Assumptions!B52 -> 3.4716726 | L20: =L17*Assumptions!B52 -> 3.7462296 | M20: =M17*Assumptions!B52 -> 4.0425 | N20: =N17*Assumptions!B52 -> 4.0425 | O20: =O17*Assumptions!B52 -> 5.4345339 | P20: =P17*Assumptions!B52 -> 7.3059143 | Q20: =Q17*Assumptions!B52 -> 9.8217041 | R20: =R17*Assumptions!B52 -> 13.203806 | S20: =S17*Assumptions!B52 -> 17.750533 | T20: =T17*Assumptions!B52 -> 23.862924 | U20: =U17*Assumptions!B52 -> 32.080116 | V20: =V17*Assumptions!B52 -> 43.126897 | W20: =W17*Assumptions!B52 -> 57.977633 | X20: =X17*Assumptions!B52 -> 77.942217 | Y20: =Y17*Assumptions!B52 -> 104.7816 | Z20: =Z17*Assumptions!B52 -> 104.7816 | AA20: =AA17*Assumptions!B52 -> 111.62798 | AB20: =AB17*Assumptions!B52 -> 118.92169 | AC20: =AC17*Assumptions!B52 -> 126.69198 | AD20: =AD17*Assumptions!B52 -> 134.96997 | AE20: =AE17*Assumptions!B52 -> 143.78884 | AF20: =AF17*Assumptions!B52 -> 153.18393 | AG20: =AG17*Assumptions!B52 -> 163.19289 | AH20: =AH17*Assumptions!B52 -> 173.85584 | AI20: =AI17*Assumptions!B52 -> 185.21549 | AJ20: =AJ17*Assumptions!B52 -> 197.31738 | AK20: =AK17*Assumptions!B52 -> 210.21 | AL20: =M20 -> 4.0425 | AM20: =Y20 -> 104.7816 | AN20: =AK20 -> 210.21
A21: Cleaning — Premium (#) | B21: =B17*Assumptions!B53 -> 0.75 | C21: =C17*Assumptions!B53 -> 0.80931371 | D21: =D17*Assumptions!B53 -> 0.87331824 | E21: =E17*Assumptions!B53 -> 0.94238457 | F21: =F17*Assumptions!B53 -> 1.016913 | G21: =G17*Assumptions!B53 -> 1.0973355 | H21: =H17*Assumptions!B53 -> 1.1841182 | I21: =I17*Assumptions!B53 -> 1.2777642 | J21: =J17*Assumptions!B53 -> 1.3788161 | K21: =K17*Assumptions!B53 -> 1.4878597 | L21: =L17*Assumptions!B53 -> 1.605527 | M21: =M17*Assumptions!B53 -> 1.7325 | N21: =N17*Assumptions!B53 -> 1.7325 | O21: =O17*Assumptions!B53 -> 2.329086 | P21: =P17*Assumptions!B53 -> 3.1311061 | Q21: =Q17*Assumptions!B53 -> 4.2093018 | R21: =R17*Assumptions!B53 -> 5.6587738 | S21: =S17*Assumptions!B53 -> 7.6073712 | T21: =T17*Assumptions!B53 -> 10.226968 | U21: =U17*Assumptions!B53 -> 13.748621 | V21: =V17*Assumptions!B53 -> 18.482956 | W21: =W17*Assumptions!B53 -> 24.847557 | X21: =X17*Assumptions!B53 -> 33.403807 | Y21: =Y17*Assumptions!B53 -> 44.9064 | Z21: =Z17*Assumptions!B53 -> 44.9064 | AA21: =AA17*Assumptions!B53 -> 47.840562 | AB21: =AB17*Assumptions!B53 -> 50.96644 | AC21: =AC17*Assumptions!B53 -> 54.296562 | AD21: =AD17*Assumptions!B53 -> 57.844273 | AE21: =AE17*Assumptions!B53 -> 61.623789 | AF21: =AF17*Assumptions!B53 -> 65.650257 | AG21: =AG17*Assumptions!B53 -> 69.939812 | AH21: =AH17*Assumptions!B53 -> 74.509645 | AI21: =AI17*Assumptions!B53 -> 79.378068 | AJ21: =AJ17*Assumptions!B53 -> 84.564592 | AK21: =AK17*Assumptions!B53 -> 90.09 | AL21: =M21 -> 1.7325 | AM21: =Y21 -> 44.9064 | AN21: =AK21 -> 90.09
A23: PM Plan Subscribers — Total (#) | B23: =Assumptions!B29 -> 5 | C23: =B23*(1+Assumptions!B32) -> 5.150597 | D23: =C23*(1+Assumptions!B32) -> 5.3057299 | E23: =D23*(1+Assumptions!B32) -> 5.4655353 | F23: =E23*(1+Assumptions!B32) -> 5.6301539 | G23: =F23*(1+Assumptions!B32) -> 5.7997308 | H23: =G23*(1+Assumptions!B32) -> 5.9744152 | I23: =H23*(1+Assumptions!B32) -> 6.154361 | J23: =I23*(1+Assumptions!B32) -> 6.3397267 | K23: =J23*(1+Assumptions!B32) -> 6.5306755 | L23: =K23*(1+Assumptions!B32) -> 6.7273755 | M23: =L23*(1+Assumptions!B32) -> 6.93 | N23: =M23 -> 6.93 | O23: =N23*(1+Assumptions!C32) -> 9.2925153 | P23: =O23*(1+Assumptions!C32) -> 12.460439 | Q23: =P23*(1+Assumptions!C32) -> 16.708343 | R23: =Q23*(1+Assumptions!C32) -> 22.404406 | S23: =R23*(1+Assumptions!C32) -> 30.042321 | T23: =S23*(1+Assumptions!C32) -> 40.284087 | U23: =T23*(1+Assumptions!C32) -> 54.017388 | V23: =U23*(1+Assumptions!C32) -> 72.432525 | W23: =V23*(1+Assumptions!C32) -> 97.125592 | X23: =W23*(1+Assumptions!C32) -> 130.2368 | Y23: =X23*(1+Assumptions!C32) -> 174.636 | Z23: =Y23 -> 174.636 | AA23: =Z23*(1+Assumptions!D32) -> 187.98671 | AB23: =AA23*(1+Assumptions!D32) -> 202.35807 | AC23: =AB23*(1+Assumptions!D32) -> 217.8281 | AD23: =AC23*(1+Assumptions!D32) -> 234.48079 | AE23: =AD23*(1+Assumptions!D32) -> 252.40657 | AF23: =AE23*(1+Assumptions!D32) -> 271.70274 | AG23: =AF23*(1+Assumptions!D32) -> 292.47409 | AH23: =AG23*(1+Assumptions!D32) -> 314.83338 | AI23: =AH23*(1+Assumptions!D32) -> 338.90202 | AJ23: =AI23*(1+Assumptions!D32) -> 364.81067 | AK23: =AJ23*(1+Assumptions!D32) -> 392.7 | AL23: =M23 -> 6.93 | AM23: =Y23 -> 174.636 | AN23: =AK23 -> 392.7
A24: Gross New PM Subs (churn-adj.) (#) | B24: =B23 -> 5 | C24: =C23-B23*(1-Assumptions!B62) -> 0.350597 | D24: =D23-C23*(1-Assumptions!B62) -> 0.36115677 | E24: =E23-D23*(1-Assumptions!B62) -> 0.3720346 | F24: =F23-E23*(1-Assumptions!B62) -> 0.38324006 | G24: =G23-F23*(1-Assumptions!B62) -> 0.39478302 | H24: =H23-G23*(1-Assumptions!B62) -> 0.40667365 | I24: =I23-H23*(1-Assumptions!B62) -> 0.41892241 | J24: =J23-I23*(1-Assumptions!B62) -> 0.4315401 | K24: =K23-J23*(1-Assumptions!B62) -> 0.44453783 | L24: =L23-K23*(1-Assumptions!B62) -> 0.45792705 | M24: =M23-L23*(1-Assumptions!B62) -> 0.47171954 | N24: =N23-M23*(1-Assumptions!B62) -> 0.2772 | O24: =O23-N23*(1-Assumptions!B62) -> 2.6397153 | P24: =P23-O23*(1-Assumptions!B62) -> 3.539624 | Q24: =Q23-P23*(1-Assumptions!B62) -> 4.7463218 | R24: =R23-Q23*(1-Assumptions!B62) -> 6.3643966 | S24: =S23-R23*(1-Assumptions!B62) -> 8.5340913 | T24: =T23-S23*(1-Assumptions!B62) -> 11.443459 | U24: =U23-T23*(1-Assumptions!B62) -> 15.344664 | V24: =V23-U23*(1-Assumptions!B62) -> 20.575833 | W24: =W23-V23*(1-Assumptions!B62) -> 27.590367 | X24: =X23-W23*(1-Assumptions!B62) -> 36.996235 | Y24: =Y23-X23*(1-Assumptions!B62) -> 49.608669 | Z24: =Z23-Y23*(1-Assumptions!B62) -> 6.98544 | AA24: =AA23-Z23*(1-Assumptions!B62) -> 20.336151 | AB24: =AB23-AA23*(1-Assumptions!B62) -> 21.890826 | AC24: =AC23-AB23*(1-Assumptions!B62) -> 23.564353 | AD24: =AD23-AC23*(1-Assumptions!B62) -> 25.365819 | AE24: =AE23-AD23*(1-Assumptions!B62) -> 27.305005 | AF24: =AF23-AE23*(1-Assumptions!B62) -> 29.39244 | AG24: =AG23-AF23*(1-Assumptions!B62) -> 31.639457 | AH24: =AH23-AG23*(1-Assumptions!B62) -> 34.058255 | AI24: =AI23-AH23*(1-Assumptions!B62) -> 36.661967 | AJ24: =AJ23-AI23*(1-Assumptions!B62) -> 39.464731 | AK24: =AK23-AJ23*(1-Assumptions!B62) -> 42.481762 | AL24: =SUM(B24:M24) -> 9.493132 | AM24: =SUM(N24:Y24) -> 187.66058 | AN24: =SUM(Z24:AK24) -> 339.14621
A25: PM Plan — Bronze (#) | B25: =B23*Assumptions!B58 -> 2.5 | C25: =C23*Assumptions!B58 -> 2.5752985 | D25: =D23*Assumptions!B58 -> 2.6528649 | E25: =E23*Assumptions!B58 -> 2.7327676 | F25: =F23*Assumptions!B58 -> 2.815077 | G25: =G23*Assumptions!B58 -> 2.8998654 | H25: =H23*Assumptions!B58 -> 2.9872076 | I25: =I23*Assumptions!B58 -> 3.0771805 | J25: =J23*Assumptions!B58 -> 3.1698633 | K25: =K23*Assumptions!B58 -> 3.2653377 | L25: =L23*Assumptions!B58 -> 3.3636877 | M25: =M23*Assumptions!B58 -> 3.465 | N25: =N23*Assumptions!B58 -> 3.465 | O25: =O23*Assumptions!B58 -> 4.6462576 | P25: =P23*Assumptions!B58 -> 6.2302193 | Q25: =Q23*Assumptions!B58 -> 8.3541715 | R25: =R23*Assumptions!B58 -> 11.202203 | S25: =S23*Assumptions!B58 -> 15.02116 | T25: =T23*Assumptions!B58 -> 20.142044 | U25: =U23*Assumptions!B58 -> 27.008694 | V25: =V23*Assumptions!B58 -> 36.216263 | W25: =W23*Assumptions!B58 -> 48.562796 | X25: =X23*Assumptions!B58 -> 65.118401 | Y25: =Y23*Assumptions!B58 -> 87.318 | Z25: =Z23*Assumptions!B58 -> 87.318 | AA25: =AA23*Assumptions!B58 -> 93.993356 | AB25: =AB23*Assumptions!B58 -> 101.17903 | AC25: =AC23*Assumptions!B58 -> 108.91405 | AD25: =AD23*Assumptions!B58 -> 117.2404 | AE25: =AE23*Assumptions!B58 -> 126.20328 | AF25: =AF23*Assumptions!B58 -> 135.85137 | AG25: =AG23*Assumptions!B58 -> 146.23705 | AH25: =AH23*Assumptions!B58 -> 157.41669 | AI25: =AI23*Assumptions!B58 -> 169.45101 | AJ25: =AJ23*Assumptions!B58 -> 182.40533 | AK25: =AK23*Assumptions!B58 -> 196.35 | AL25: =M25 -> 3.465 | AM25: =Y25 -> 87.318 | AN25: =AK25 -> 196.35
A26: PM Plan — Silver (#) | B26: =B23*Assumptions!B59 -> 1.75 | C26: =C23*Assumptions!B59 -> 1.802709 | D26: =D23*Assumptions!B59 -> 1.8570055 | E26: =E23*Assumptions!B59 -> 1.9129374 | F26: =F23*Assumptions!B59 -> 1.9705539 | G26: =G23*Assumptions!B59 -> 2.0299058 | H26: =H23*Assumptions!B59 -> 2.0910453 | I26: =I23*Assumptions!B59 -> 2.1540264 | J26: =J23*Assumptions!B59 -> 2.2189043 | K26: =K23*Assumptions!B59 -> 2.2857364 | L26: =L23*Assumptions!B59 -> 2.3545814 | M26: =M23*Assumptions!B59 -> 2.4255 | N26: =N23*Assumptions!B59 -> 2.4255 | O26: =O23*Assumptions!B59 -> 3.2523803 | P26: =P23*Assumptions!B59 -> 4.3611535 | Q26: =Q23*Assumptions!B59 -> 5.84792 | R26: =R23*Assumptions!B59 -> 7.841542 | S26: =S23*Assumptions!B59 -> 10.514812 | T26: =T23*Assumptions!B59 -> 14.099431 | U26: =U23*Assumptions!B59 -> 18.906086 | V26: =V23*Assumptions!B59 -> 25.351384 | W26: =W23*Assumptions!B59 -> 33.993957 | X26: =X23*Assumptions!B59 -> 45.582881 | Y26: =Y23*Assumptions!B59 -> 61.1226 | Z26: =Z23*Assumptions!B59 -> 61.1226 | AA26: =AA23*Assumptions!B59 -> 65.795349 | AB26: =AB23*Assumptions!B59 -> 70.825324 | AC26: =AC23*Assumptions!B59 -> 76.239835 | AD26: =AD23*Assumptions!B59 -> 82.068278 | AE26: =AE23*Assumptions!B59 -> 88.342299 | AF26: =AF23*Assumptions!B59 -> 95.095961 | AG26: =AG23*Assumptions!B59 -> 102.36593 | AH26: =AH23*Assumptions!B59 -> 110.19168 | AI26: =AI23*Assumptions!B59 -> 118.61571 | AJ26: =AJ23*Assumptions!B59 -> 127.68373 | AK26: =AK23*Assumptions!B59 -> 137.445 | AL26: =M26 -> 2.4255 | AM26: =Y26 -> 61.1226 | AN26: =AK26 -> 137.445
A27: PM Plan — Gold (#) | B27: =B23*Assumptions!B60 -> 0.75 | C27: =C23*Assumptions!B60 -> 0.77258955 | D27: =D23*Assumptions!B60 -> 0.79585948 | E27: =E23*Assumptions!B60 -> 0.81983029 | F27: =F23*Assumptions!B60 -> 0.84452309 | G27: =G23*Assumptions!B60 -> 0.86995962 | H27: =H23*Assumptions!B60 -> 0.89616228 | I27: =I23*Assumptions!B60 -> 0.92315415 | J27: =J23*Assumptions!B60 -> 0.950959 | K27: =K23*Assumptions!B60 -> 0.97960132 | L27: =L23*Assumptions!B60 -> 1.0091063 | M27: =M23*Assumptions!B60 -> 1.0395 | N27: =N23*Assumptions!B60 -> 1.0395 | O27: =O23*Assumptions!B60 -> 1.3938773 | P27: =P23*Assumptions!B60 -> 1.8690658 | Q27: =Q23*Assumptions!B60 -> 2.5062514 | R27: =R23*Assumptions!B60 -> 3.3606609 | S27: =S23*Assumptions!B60 -> 4.5063481 | T27: =T23*Assumptions!B60 -> 6.0426131 | U27: =U23*Assumptions!B60 -> 8.1026082 | V27: =V23*Assumptions!B60 -> 10.864879 | W27: =W23*Assumptions!B60 -> 14.568839 | X27: =X23*Assumptions!B60 -> 19.53552 | Y27: =Y23*Assumptions!B60 -> 26.1954 | Z27: =Z23*Assumptions!B60 -> 26.1954 | AA27: =AA23*Assumptions!B60 -> 28.198007 | AB27: =AB23*Assumptions!B60 -> 30.35371 | AC27: =AC23*Assumptions!B60 -> 32.674215 | AD27: =AD23*Assumptions!B60 -> 35.172119 | AE27: =AE23*Assumptions!B60 -> 37.860985 | AF27: =AF23*Assumptions!B60 -> 40.755412 | AG27: =AG23*Assumptions!B60 -> 43.871114 | AH27: =AH23*Assumptions!B60 -> 47.225007 | AI27: =AI23*Assumptions!B60 -> 50.835302 | AJ27: =AJ23*Assumptions!B60 -> 54.7216 | AK27: =AK23*Assumptions!B60 -> 58.905 | AL27: =M27 -> 1.0395 | AM27: =Y27 -> 26.1954 | AN27: =AK27 -> 58.905
A29: Note: FY columns show Dec value for stocks/ratios (Downloads, Penetration, Active Customers, Subscriber counts) and SUM for flows (Net New, Jobs, Gross Adds).

Sheet Monthly P&L
A1: MONTHLY P&L — THROUGH EBITDA
A2: All figures QAR. Costs shown as negative. Driven by Volume & Funnel Build and Assumptions.
B4: Year 1 | N4: Year 2 | Z4: Year 3 | AL4: FY1 | AM4: FY2 | AN4: FY3
B5: Y1M1 | C5: Y1M2 | D5: Y1M3 | E5: Y1M4 | F5: Y1M5 | G5: Y1M6 | H5: Y1M7 | I5: Y1M8 | J5: Y1M9 | K5: Y1M10 | L5: Y1M11 | M5: Y1M12 | N5: Y2M1 | O5: Y2M2 | P5: Y2M3 | Q5: Y2M4 | R5: Y2M5 | S5: Y2M6 | T5: Y2M7 | U5: Y2M8 | V5: Y2M9 | W5: Y2M10 | X5: Y2M11 | Y5: Y2M12 | Z5: Y3M1 | AA5: Y3M2 | AB5: Y3M3 | AC5: Y3M4 | AD5: Y3M5 | AE5: Y3M6 | AF5: Y3M7 | AG5: Y3M8 | AH5: Y3M9 | AI5: Y3M10 | AJ5: Y3M11 | AK5: Y3M12 | AL5: FY1 Total | AM5: FY2 Total | AN5: FY3 Total
A7: REVENUE
A8: In-House Job Revenue | B8: ='Volume & Funnel Build'!B14*Assumptions!B35 -> 3341.25 | C8: ='Volume & Funnel Build'!C14*Assumptions!B35 -> 3475.012 | D8: ='Volume & Funnel Build'!D14*Assumptions!B35 -> 3614.129 | E8: ='Volume & Funnel Build'!E14*Assumptions!B35 -> 3758.8153 | F8: ='Volume & Funnel Build'!F14*Assumptions!B35 -> 3909.2939 | G8: ='Volume & Funnel Build'!G14*Assumptions!B35 -> 4065.7967 | H8: ='Volume & Funnel Build'!H14*Assumptions!B35 -> 4228.5649 | I8: ='Volume & Funnel Build'!I14*Assumptions!B35 -> 4397.8493 | J8: ='Volume & Funnel Build'!J14*Assumptions!B35 -> 4573.9107 | K8: ='Volume & Funnel Build'!K14*Assumptions!B35 -> 4757.0204 | L8: ='Volume & Funnel Build'!L14*Assumptions!B35 -> 4947.4607 | M8: ='Volume & Funnel Build'!M14*Assumptions!B35 -> 5145.525 | N8: ='Volume & Funnel Build'!N14*Assumptions!B35 -> 4939.704 | O8: ='Volume & Funnel Build'!O14*Assumptions!B35 -> 6424.1638 | P8: ='Volume & Funnel Build'!P14*Assumptions!B35 -> 8354.7275 | Q8: ='Volume & Funnel Build'!Q14*Assumptions!B35 -> 10865.456 | R8: ='Volume & Funnel Build'!R14*Assumptions!B35 -> 14130.699 | S8: ='Volume & Funnel Build'!S14*Assumptions!B35 -> 18377.2 | T8: ='Volume & Funnel Build'!T14*Assumptions!B35 -> 23899.841 | U8: ='Volume & Funnel Build'!U14*Assumptions!B35 -> 31082.125 | V8: ='Volume & Funnel Build'!V14*Assumptions!B35 -> 40422.799 | W8: ='Volume & Funnel Build'!W14*Assumptions!B35 -> 52570.495 | X8: ='Volume & Funnel Build'!X14*Assumptions!B35 -> 68368.767 | Y8: ='Volume & Funnel Build'!Y14*Assumptions!B35 -> 88914.672 | Z8: ='Volume & Funnel Build'!Z14*Assumptions!B35 -> 82328.4 | AA8: ='Volume & Funnel Build'!AA14*Assumptions!B35 -> 86241.786 | AB8: ='Volume & Funnel Build'!AB14*Assumptions!B35 -> 90341.191 | AC8: ='Volume & Funnel Build'!AC14*Assumptions!B35 -> 94635.456 | AD8: ='Volume & Funnel Build'!AD14*Assumptions!B35 -> 99133.844 | AE8: ='Volume & Funnel Build'!AE14*Assumptions!B35 -> 103846.06 | AF8: ='Volume & Funnel Build'!AF14*Assumptions!B35 -> 108782.26 | AG8: ='Volume & Funnel Build'!AG14*Assumptions!B35 -> 113953.1 | AH8: ='Volume & Funnel Build'!AH14*Assumptions!B35 -> 119369.73 | AI8: ='Volume & Funnel Build'!AI14*Assumptions!B35 -> 125043.84 | AJ8: ='Volume & Funnel Build'!AJ14*Assumptions!B35 -> 130987.65 | AK8: ='Volume & Funnel Build'!AK14*Assumptions!B35 -> 137214 | AL8: =SUM(B8:M8) -> 50214.628 | AM8: =SUM(N8:Y8) -> 368350.65 | AN8: =SUM(Z8:AK8) -> 1291877.3
A9: Marketplace Commission Revenue | B9: ='Volume & Funnel Build'!B15*Assumptions!B35*Assumptions!B36 -> 245.025 | C9: ='Volume & Funnel Build'!C15*Assumptions!B35*Assumptions!B36 -> 254.83421 | D9: ='Volume & Funnel Build'!D15*Assumptions!B35*Assumptions!B36 -> 265.03613 | E9: ='Volume & Funnel Build'!E15*Assumptions!B35*Assumptions!B36 -> 275.64646 | F9: ='Volume & Funnel Build'!F15*Assumptions!B35*Assumptions!B36 -> 286.68155 | G9: ='Volume & Funnel Build'!G15*Assumptions!B35*Assumptions!B36 -> 298.15843 | H9: ='Volume & Funnel Build'!H15*Assumptions!B35*Assumptions!B36 -> 310.09476 | I9: ='Volume & Funnel Build'!I15*Assumptions!B35*Assumptions!B36 -> 322.50895 | J9: ='Volume & Funnel Build'!J15*Assumptions!B35*Assumptions!B36 -> 335.42012 | K9: ='Volume & Funnel Build'!K15*Assumptions!B35*Assumptions!B36 -> 348.84816 | L9: ='Volume & Funnel Build'!L15*Assumptions!B35*Assumptions!B36 -> 362.81379 | M9: ='Volume & Funnel Build'!M15*Assumptions!B35*Assumptions!B36 -> 377.3385 | N9: ='Volume & Funnel Build'!N15*Assumptions!B35*Assumptions!B36 -> 724.48992 | O9: ='Volume & Funnel Build'!O15*Assumptions!B35*Assumptions!B36 -> 942.2107 | P9: ='Volume & Funnel Build'!P15*Assumptions!B35*Assumptions!B36 -> 1225.36 | Q9: ='Volume & Funnel Build'!Q15*Assumptions!B35*Assumptions!B36 -> 1593.6003 | R9: ='Volume & Funnel Build'!R15*Assumptions!B35*Assumptions!B36 -> 2072.5026 | S9: ='Volume & Funnel Build'!S15*Assumptions!B35*Assumptions!B36 -> 2695.3226 | T9: ='Volume & Funnel Build'!T15*Assumptions!B35*Assumptions!B36 -> 3505.3101 | U9: ='Volume & Funnel Build'!U15*Assumptions!B35*Assumptions!B36 -> 4558.7117 | V9: ='Volume & Funnel Build'!V15*Assumptions!B35*Assumptions!B36 -> 5928.6772 | W9: ='Volume & Funnel Build'!W15*Assumptions!B35*Assumptions!B36 -> 7710.3393 | X9: ='Volume & Funnel Build'!X15*Assumptions!B35*Assumptions!B36 -> 10027.419 | Y9: ='Volume & Funnel Build'!Y15*Assumptions!B35*Assumptions!B36 -> 13040.819 | Z9: ='Volume & Funnel Build'!Z15*Assumptions!B35*Assumptions!B36 -> 18112.248 | AA9: ='Volume & Funnel Build'!AA15*Assumptions!B35*Assumptions!B36 -> 18973.193 | AB9: ='Volume & Funnel Build'!AB15*Assumptions!B35*Assumptions!B36 -> 19875.062 | AC9: ='Volume & Funnel Build'!AC15*Assumptions!B35*Assumptions!B36 -> 20819.8 | AD9: ='Volume & Funnel Build'!AD15*Assumptions!B35*Assumptions!B36 -> 21809.446 | AE9: ='Volume & Funnel Build'!AE15*Assumptions!B35*Assumptions!B36 -> 22846.133 | AF9: ='Volume & Funnel Build'!AF15*Assumptions!B35*Assumptions!B36 -> 23932.098 | AG9: ='Volume & Funnel Build'!AG15*Assumptions!B35*Assumptions!B36 -> 25069.682 | AH9: ='Volume & Funnel Build'!AH15*Assumptions!B35*Assumptions!B36 -> 26261.341 | AI9: ='Volume & Funnel Build'!AI15*Assumptions!B35*Assumptions!B36 -> 27509.644 | AJ9: ='Volume & Funnel Build'!AJ15*Assumptions!B35*Assumptions!B36 -> 28817.283 | AK9: ='Volume & Funnel Build'!AK15*Assumptions!B35*Assumptions!B36 -> 30187.08 | AL9: =SUM(B9:M9) -> 3682.406 | AM9: =SUM(N9:Y9) -> 54024.762 | AN9: =SUM(Z9:AK9) -> 284213.01
A10: Booking Fee Revenue | B10: ='Volume & Funnel Build'!B13*Assumptions!B37 -> 0 | C10: ='Volume & Funnel Build'!C13*Assumptions!B37 -> 0 | D10: ='Volume & Funnel Build'!D13*Assumptions!B37 -> 0 | E10: ='Volume & Funnel Build'!E13*Assumptions!B37 -> 0 | F10: ='Volume & Funnel Build'!F13*Assumptions!B37 -> 0 | G10: ='Volume & Funnel Build'!G13*Assumptions!B37 -> 0 | H10: ='Volume & Funnel Build'!H13*Assumptions!B37 -> 0 | I10: ='Volume & Funnel Build'!I13*Assumptions!B37 -> 0 | J10: ='Volume & Funnel Build'!J13*Assumptions!B37 -> 0 | K10: ='Volume & Funnel Build'!K13*Assumptions!B37 -> 0 | L10: ='Volume & Funnel Build'!L13*Assumptions!B37 -> 0 | M10: ='Volume & Funnel Build'!M13*Assumptions!B37 -> 0 | N10: ='Volume & Funnel Build'!N13*Assumptions!B37 -> 0 | O10: ='Volume & Funnel Build'!O13*Assumptions!B37 -> 0 | P10: ='Volume & Funnel Build'!P13*Assumptions!B37 -> 0 | Q10: ='Volume & Funnel Build'!Q13*Assumptions!B37 -> 0 | R10: ='Volume & Funnel Build'!R13*Assumptions!B37 -> 0 | S10: ='Volume & Funnel Build'!S13*Assumptions!B37 -> 0 | T10: ='Volume & Funnel Build'!T13*Assumptions!B37 -> 0 | U10: ='Volume & Funnel Build'!U13*Assumptions!B37 -> 0 | V10: ='Volume & Funnel Build'!V13*Assumptions!B37 -> 0 | W10: ='Volume & Funnel Build'!W13*Assumptions!B37 -> 0 | X10: ='Volume & Funnel Build'!X13*Assumptions!B37 -> 0 | Y10: ='Volume & Funnel Build'!Y13*Assumptions!B37 -> 0 | Z10: ='Volume & Funnel Build'!Z13*Assumptions!B37 -> 0 | AA10: ='Volume & Funnel Build'!AA13*Assumptions!B37 -> 0 | AB10: ='Volume & Funnel Build'!AB13*Assumptions!B37 -> 0 | AC10: ='Volume & Funnel Build'!AC13*Assumptions!B37 -> 0 | AD10: ='Volume & Funnel Build'!AD13*Assumptions!B37 -> 0 | AE10: ='Volume & Funnel Build'!AE13*Assumptions!B37 -> 0 | AF10: ='Volume & Funnel Build'!AF13*Assumptions!B37 -> 0 | AG10: ='Volume & Funnel Build'!AG13*Assumptions!B37 -> 0 | AH10: ='Volume & Funnel Build'!AH13*Assumptions!B37 -> 0 | AI10: ='Volume & Funnel Build'!AI13*Assumptions!B37 -> 0 | AJ10: ='Volume & Funnel Build'!AJ13*Assumptions!B37 -> 0 | AK10: ='Volume & Funnel Build'!AK13*Assumptions!B37 -> 0 | AL10: =SUM(B10:M10) -> 0 | AM10: =SUM(N10:Y10) -> 0 | AN10: =SUM(Z10:AK10) -> 0
A11: Emergency Premium Revenue | B11: ='Volume & Funnel Build'!B13*Assumptions!B39*Assumptions!B35*(Assumptions!B38-1) -> -49.005 | C11: ='Volume & Funnel Build'!C13*Assumptions!B39*Assumptions!B35*(Assumptions!B38-1) -> -50.966843 | D11: ='Volume & Funnel Build'!D13*Assumptions!B39*Assumptions!B35*(Assumptions!B38-1) -> -53.007225 | E11: ='Volume & Funnel Build'!E13*Assumptions!B39*Assumptions!B35*(Assumptions!B38-1) -> -55.129291 | F11: ='Volume & Funnel Build'!F13*Assumptions!B39*Assumptions!B35*(Assumptions!B38-1) -> -57.336311 | G11: ='Volume & Funnel Build'!G13*Assumptions!B39*Assumptions!B35*(Assumptions!B38-1) -> -59.631685 | H11: ='Volume & Funnel Build'!H13*Assumptions!B39*Assumptions!B35*(Assumptions!B38-1) -> -62.018952 | I11: ='Volume & Funnel Build'!I13*Assumptions!B39*Assumptions!B35*(Assumptions!B38-1) -> -64.501789 | J11: ='Volume & Funnel Build'!J13*Assumptions!B39*Assumptions!B35*(Assumptions!B38-1) -> -67.084023 | K11: ='Volume & Funnel Build'!K13*Assumptions!B39*Assumptions!B35*(Assumptions!B38-1) -> -69.769633 | L11: ='Volume & Funnel Build'!L13*Assumptions!B39*Assumptions!B35*(Assumptions!B38-1) -> -72.562757 | M11: ='Volume & Funnel Build'!M13*Assumptions!B39*Assumptions!B35*(Assumptions!B38-1) -> -75.4677 | N11: ='Volume & Funnel Build'!N13*Assumptions!B39*Assumptions!B35*(Assumptions!B38-1) -> -90.56124 | O11: ='Volume & Funnel Build'!O13*Assumptions!B39*Assumptions!B35*(Assumptions!B38-1) -> -117.77634 | P11: ='Volume & Funnel Build'!P13*Assumptions!B39*Assumptions!B35*(Assumptions!B38-1) -> -153.17 | Q11: ='Volume & Funnel Build'!Q13*Assumptions!B39*Assumptions!B35*(Assumptions!B38-1) -> -199.20003 | R11: ='Volume & Funnel Build'!R13*Assumptions!B39*Assumptions!B35*(Assumptions!B38-1) -> -259.06282 | S11: ='Volume & Funnel Build'!S13*Assumptions!B39*Assumptions!B35*(Assumptions!B38-1) -> -336.91533 | T11: ='Volume & Funnel Build'!T13*Assumptions!B39*Assumptions!B35*(Assumptions!B38-1) -> -438.16376 | U11: ='Volume & Funnel Build'!U13*Assumptions!B39*Assumptions!B35*(Assumptions!B38-1) -> -569.83896 | V11: ='Volume & Funnel Build'!V13*Assumptions!B39*Assumptions!B35*(Assumptions!B38-1) -> -741.08465 | W11: ='Volume & Funnel Build'!W13*Assumptions!B39*Assumptions!B35*(Assumptions!B38-1) -> -963.79241 | X11: ='Volume & Funnel Build'!X13*Assumptions!B39*Assumptions!B35*(Assumptions!B38-1) -> -1253.4274 | Y11: ='Volume & Funnel Build'!Y13*Assumptions!B39*Assumptions!B35*(Assumptions!B38-1) -> -1630.1023 | Z11: ='Volume & Funnel Build'!Z13*Assumptions!B39*Assumptions!B35*(Assumptions!B38-1) -> -1811.2248 | AA11: ='Volume & Funnel Build'!AA13*Assumptions!B39*Assumptions!B35*(Assumptions!B38-1) -> -1897.3193 | AB11: ='Volume & Funnel Build'!AB13*Assumptions!B39*Assumptions!B35*(Assumptions!B38-1) -> -1987.5062 | AC11: ='Volume & Funnel Build'!AC13*Assumptions!B39*Assumptions!B35*(Assumptions!B38-1) -> -2081.98 | AD11: ='Volume & Funnel Build'!AD13*Assumptions!B39*Assumptions!B35*(Assumptions!B38-1) -> -2180.9446 | AE11: ='Volume & Funnel Build'!AE13*Assumptions!B39*Assumptions!B35*(Assumptions!B38-1) -> -2284.6133 | AF11: ='Volume & Funnel Build'!AF13*Assumptions!B39*Assumptions!B35*(Assumptions!B38-1) -> -2393.2098 | AG11: ='Volume & Funnel Build'!AG13*Assumptions!B39*Assumptions!B35*(Assumptions!B38-1) -> -2506.9682 | AH11: ='Volume & Funnel Build'!AH13*Assumptions!B39*Assumptions!B35*(Assumptions!B38-1) -> -2626.1341 | AI11: ='Volume & Funnel Build'!AI13*Assumptions!B39*Assumptions!B35*(Assumptions!B38-1) -> -2750.9644 | AJ11: ='Volume & Funnel Build'!AJ13*Assumptions!B39*Assumptions!B35*(Assumptions!B38-1) -> -2881.7283 | AK11: ='Volume & Funnel Build'!AK13*Assumptions!B39*Assumptions!B35*(Assumptions!B38-1) -> -3018.708 | AL11: =SUM(B11:M11) -> -736.48121 | AM11: =SUM(N11:Y11) -> -6753.0953 | AN11: =SUM(Z11:AK11) -> -28421.301
A12: Cleaning Subscription Revenue | B12: ='Volume & Funnel Build'!B19*Assumptions!B48+'Volume & Funnel Build'!B20*Assumptions!B49+'Volume & Funnel Build'!B21*Assumptions!B50 -> 2815 | C12: ='Volume & Funnel Build'!C19*Assumptions!B48+'Volume & Funnel Build'!C20*Assumptions!B49+'Volume & Funnel Build'!C21*Assumptions!B50 -> 3037.6241 | D12: ='Volume & Funnel Build'!D19*Assumptions!B48+'Volume & Funnel Build'!D20*Assumptions!B49+'Volume & Funnel Build'!D21*Assumptions!B50 -> 3277.8545 | E12: ='Volume & Funnel Build'!E19*Assumptions!B48+'Volume & Funnel Build'!E20*Assumptions!B49+'Volume & Funnel Build'!E21*Assumptions!B50 -> 3537.0834 | F12: ='Volume & Funnel Build'!F19*Assumptions!B48+'Volume & Funnel Build'!F20*Assumptions!B49+'Volume & Funnel Build'!F21*Assumptions!B50 -> 3816.8135 | G12: ='Volume & Funnel Build'!G19*Assumptions!B48+'Volume & Funnel Build'!G20*Assumptions!B49+'Volume & Funnel Build'!G21*Assumptions!B50 -> 4118.666 | H12: ='Volume & Funnel Build'!H19*Assumptions!B48+'Volume & Funnel Build'!H20*Assumptions!B49+'Volume & Funnel Build'!H21*Assumptions!B50 -> 4444.3905 | I12: ='Volume & Funnel Build'!I19*Assumptions!B48+'Volume & Funnel Build'!I20*Assumptions!B49+'Volume & Funnel Build'!I21*Assumptions!B50 -> 4795.8748 | J12: ='Volume & Funnel Build'!J19*Assumptions!B48+'Volume & Funnel Build'!J20*Assumptions!B49+'Volume & Funnel Build'!J21*Assumptions!B50 -> 5175.1564 | K12: ='Volume & Funnel Build'!K19*Assumptions!B48+'Volume & Funnel Build'!K20*Assumptions!B49+'Volume & Funnel Build'!K21*Assumptions!B50 -> 5584.4333 | L12: ='Volume & Funnel Build'!L19*Assumptions!B48+'Volume & Funnel Build'!L20*Assumptions!B49+'Volume & Funnel Build'!L21*Assumptions!B50 -> 6026.0779 | M12: ='Volume & Funnel Build'!M19*Assumptions!B48+'Volume & Funnel Build'!M20*Assumptions!B49+'Volume & Funnel Build'!M21*Assumptions!B50 -> 6502.65 | N12: ='Volume & Funnel Build'!N19*Assumptions!B48+'Volume & Funnel Build'!N20*Assumptions!B49+'Volume & Funnel Build'!N21*Assumptions!B50 -> 6502.65 | O12: ='Volume & Funnel Build'!O19*Assumptions!B48+'Volume & Funnel Build'!O20*Assumptions!B49+'Volume & Funnel Build'!O21*Assumptions!B50 -> 8741.8359 | P12: ='Volume & Funnel Build'!P19*Assumptions!B48+'Volume & Funnel Build'!P20*Assumptions!B49+'Volume & Funnel Build'!P21*Assumptions!B50 -> 11752.085 | Q12: ='Volume & Funnel Build'!Q19*Assumptions!B48+'Volume & Funnel Build'!Q20*Assumptions!B49+'Volume & Funnel Build'!Q21*Assumptions!B50 -> 15798.913 | R12: ='Volume & Funnel Build'!R19*Assumptions!B48+'Volume & Funnel Build'!R20*Assumptions!B49+'Volume & Funnel Build'!R21*Assumptions!B50 -> 21239.264 | S12: ='Volume & Funnel Build'!S19*Assumptions!B48+'Volume & Funnel Build'!S20*Assumptions!B49+'Volume & Funnel Build'!S21*Assumptions!B50 -> 28553 | T12: ='Volume & Funnel Build'!T19*Assumptions!B48+'Volume & Funnel Build'!T20*Assumptions!B49+'Volume & Funnel Build'!T21*Assumptions!B50 -> 38385.218 | U12: ='Volume & Funnel Build'!U19*Assumptions!B48+'Volume & Funnel Build'!U20*Assumptions!B49+'Volume & Funnel Build'!U21*Assumptions!B50 -> 51603.159 | V12: ='Volume & Funnel Build'!V19*Assumptions!B48+'Volume & Funnel Build'!V20*Assumptions!B49+'Volume & Funnel Build'!V21*Assumptions!B50 -> 69372.694 | W12: ='Volume & Funnel Build'!W19*Assumptions!B48+'Volume & Funnel Build'!W20*Assumptions!B49+'Volume & Funnel Build'!W21*Assumptions!B50 -> 93261.164 | X12: ='Volume & Funnel Build'!X19*Assumptions!B48+'Volume & Funnel Build'!X20*Assumptions!B49+'Volume & Funnel Build'!X21*Assumptions!B50 -> 125375.62 | Y12: ='Volume & Funnel Build'!Y19*Assumptions!B48+'Volume & Funnel Build'!Y20*Assumptions!B49+'Volume & Funnel Build'!Y21*Assumptions!B50 -> 168548.69 | Z12: ='Volume & Funnel Build'!Z19*Assumptions!B48+'Volume & Funnel Build'!Z20*Assumptions!B49+'Volume & Funnel Build'!Z21*Assumptions!B50 -> 168548.69 | AA12: ='Volume & Funnel Build'!AA19*Assumptions!B48+'Volume & Funnel Build'!AA20*Assumptions!B49+'Volume & Funnel Build'!AA21*Assumptions!B50 -> 179561.58 | AB12: ='Volume & Funnel Build'!AB19*Assumptions!B48+'Volume & Funnel Build'!AB20*Assumptions!B49+'Volume & Funnel Build'!AB21*Assumptions!B50 -> 191294.04 | AC12: ='Volume & Funnel Build'!AC19*Assumptions!B48+'Volume & Funnel Build'!AC20*Assumptions!B49+'Volume & Funnel Build'!AC21*Assumptions!B50 -> 203793.1 | AD12: ='Volume & Funnel Build'!AD19*Assumptions!B48+'Volume & Funnel Build'!AD20*Assumptions!B49+'Volume & Funnel Build'!AD21*Assumptions!B50 -> 217108.84 | AE12: ='Volume & Funnel Build'!AE19*Assumptions!B48+'Volume & Funnel Build'!AE20*Assumptions!B49+'Volume & Funnel Build'!AE21*Assumptions!B50 -> 231294.62 | AF12: ='Volume & Funnel Build'!AF19*Assumptions!B48+'Volume & Funnel Build'!AF20*Assumptions!B49+'Volume & Funnel Build'!AF21*Assumptions!B50 -> 246407.3 | AG12: ='Volume & Funnel Build'!AG19*Assumptions!B48+'Volume & Funnel Build'!AG20*Assumptions!B49+'Volume & Funnel Build'!AG21*Assumptions!B50 -> 262507.43 | AH12: ='Volume & Funnel Build'!AH19*Assumptions!B48+'Volume & Funnel Build'!AH20*Assumptions!B49+'Volume & Funnel Build'!AH21*Assumptions!B50 -> 279659.53 | AI12: ='Volume & Funnel Build'!AI19*Assumptions!B48+'Volume & Funnel Build'!AI20*Assumptions!B49+'Volume & Funnel Build'!AI21*Assumptions!B50 -> 297932.35 | AJ12: ='Volume & Funnel Build'!AJ19*Assumptions!B48+'Volume & Funnel Build'!AJ20*Assumptions!B49+'Volume & Funnel Build'!AJ21*Assumptions!B50 -> 317399.1 | AK12: ='Volume & Funnel Build'!AK19*Assumptions!B48+'Volume & Funnel Build'!AK20*Assumptions!B49+'Volume & Funnel Build'!AK21*Assumptions!B50 -> 338137.8 | AL12: =SUM(B12:M12) -> 53131.624 | AM12: =SUM(N12:Y12) -> 639134.29 | AN12: =SUM(Z12:AK12) -> 2933644.4
A13: PM Plan Subscription Revenue | B13: ='Volume & Funnel Build'!B25*Assumptions!B55+'Volume & Funnel Build'!B26*Assumptions!B56+'Volume & Funnel Build'!B27*Assumptions!B57 -> 670 | C13: ='Volume & Funnel Build'!C25*Assumptions!B55+'Volume & Funnel Build'!C26*Assumptions!B56+'Volume & Funnel Build'!C27*Assumptions!B57 -> 690.18 | D13: ='Volume & Funnel Build'!D25*Assumptions!B55+'Volume & Funnel Build'!D26*Assumptions!B56+'Volume & Funnel Build'!D27*Assumptions!B57 -> 710.96781 | E13: ='Volume & Funnel Build'!E25*Assumptions!B55+'Volume & Funnel Build'!E26*Assumptions!B56+'Volume & Funnel Build'!E27*Assumptions!B57 -> 732.38173 | F13: ='Volume & Funnel Build'!F25*Assumptions!B55+'Volume & Funnel Build'!F26*Assumptions!B56+'Volume & Funnel Build'!F27*Assumptions!B57 -> 754.44063 | G13: ='Volume & Funnel Build'!G25*Assumptions!B55+'Volume & Funnel Build'!G26*Assumptions!B56+'Volume & Funnel Build'!G27*Assumptions!B57 -> 777.16393 | H13: ='Volume & Funnel Build'!H25*Assumptions!B55+'Volume & Funnel Build'!H26*Assumptions!B56+'Volume & Funnel Build'!H27*Assumptions!B57 -> 800.57164 | I13: ='Volume & Funnel Build'!I25*Assumptions!B55+'Volume & Funnel Build'!I26*Assumptions!B56+'Volume & Funnel Build'!I27*Assumptions!B57 -> 824.68438 | J13: ='Volume & Funnel Build'!J25*Assumptions!B55+'Volume & Funnel Build'!J26*Assumptions!B56+'Volume & Funnel Build'!J27*Assumptions!B57 -> 849.52338 | K13: ='Volume & Funnel Build'!K25*Assumptions!B55+'Volume & Funnel Build'!K26*Assumptions!B56+'Volume & Funnel Build'!K27*Assumptions!B57 -> 875.11051 | L13: ='Volume & Funnel Build'!L25*Assumptions!B55+'Volume & Funnel Build'!L26*Assumptions!B56+'Volume & Funnel Build'!L27*Assumptions!B57 -> 901.46831 | M13: ='Volume & Funnel Build'!M25*Assumptions!B55+'Volume & Funnel Build'!M26*Assumptions!B56+'Volume & Funnel Build'!M27*Assumptions!B57 -> 928.62 | N13: ='Volume & Funnel Build'!N25*Assumptions!B55+'Volume & Funnel Build'!N26*Assumptions!B56+'Volume & Funnel Build'!N27*Assumptions!B57 -> 928.62 | O13: ='Volume & Funnel Build'!O25*Assumptions!B55+'Volume & Funnel Build'!O26*Assumptions!B56+'Volume & Funnel Build'!O27*Assumptions!B57 -> 1245.197 | P13: ='Volume & Funnel Build'!P25*Assumptions!B55+'Volume & Funnel Build'!P26*Assumptions!B56+'Volume & Funnel Build'!P27*Assumptions!B57 -> 1669.6988 | Q13: ='Volume & Funnel Build'!Q25*Assumptions!B55+'Volume & Funnel Build'!Q26*Assumptions!B56+'Volume & Funnel Build'!Q27*Assumptions!B57 -> 2238.918 | R13: ='Volume & Funnel Build'!R25*Assumptions!B55+'Volume & Funnel Build'!R26*Assumptions!B56+'Volume & Funnel Build'!R27*Assumptions!B57 -> 3002.1904 | S13: ='Volume & Funnel Build'!S25*Assumptions!B55+'Volume & Funnel Build'!S26*Assumptions!B56+'Volume & Funnel Build'!S27*Assumptions!B57 -> 4025.671 | T13: ='Volume & Funnel Build'!T25*Assumptions!B55+'Volume & Funnel Build'!T26*Assumptions!B56+'Volume & Funnel Build'!T27*Assumptions!B57 -> 5398.0677 | U13: ='Volume & Funnel Build'!U25*Assumptions!B55+'Volume & Funnel Build'!U26*Assumptions!B56+'Volume & Funnel Build'!U27*Assumptions!B57 -> 7238.33 | V13: ='Volume & Funnel Build'!V25*Assumptions!B55+'Volume & Funnel Build'!V26*Assumptions!B56+'Volume & Funnel Build'!V27*Assumptions!B57 -> 9705.9584 | W13: ='Volume & Funnel Build'!W25*Assumptions!B55+'Volume & Funnel Build'!W26*Assumptions!B56+'Volume & Funnel Build'!W27*Assumptions!B57 -> 13014.829 | X13: ='Volume & Funnel Build'!X25*Assumptions!B55+'Volume & Funnel Build'!X26*Assumptions!B56+'Volume & Funnel Build'!X27*Assumptions!B57 -> 17451.732 | Y13: ='Volume & Funnel Build'!Y25*Assumptions!B55+'Volume & Funnel Build'!Y26*Assumptions!B56+'Volume & Funnel Build'!Y27*Assumptions!B57 -> 23401.224 | Z13: ='Volume & Funnel Build'!Z25*Assumptions!B55+'Volume & Funnel Build'!Z26*Assumptions!B56+'Volume & Funnel Build'!Z27*Assumptions!B57 -> 23401.224 | AA13: ='Volume & Funnel Build'!AA25*Assumptions!B55+'Volume & Funnel Build'!AA26*Assumptions!B56+'Volume & Funnel Build'!AA27*Assumptions!B57 -> 25190.219 | AB13: ='Volume & Funnel Build'!AB25*Assumptions!B55+'Volume & Funnel Build'!AB26*Assumptions!B56+'Volume & Funnel Build'!AB27*Assumptions!B57 -> 27115.981 | AC13: ='Volume & Funnel Build'!AC25*Assumptions!B55+'Volume & Funnel Build'!AC26*Assumptions!B56+'Volume & Funnel Build'!AC27*Assumptions!B57 -> 29188.965 | AD13: ='Volume & Funnel Build'!AD25*Assumptions!B55+'Volume & Funnel Build'!AD26*Assumptions!B56+'Volume & Funnel Build'!AD27*Assumptions!B57 -> 31420.426 | AE13: ='Volume & Funnel Build'!AE25*Assumptions!B55+'Volume & Funnel Build'!AE26*Assumptions!B56+'Volume & Funnel Build'!AE27*Assumptions!B57 -> 33822.48 | AF13: ='Volume & Funnel Build'!AF25*Assumptions!B55+'Volume & Funnel Build'!AF26*Assumptions!B56+'Volume & Funnel Build'!AF27*Assumptions!B57 -> 36408.168 | AG13: ='Volume & Funnel Build'!AG25*Assumptions!B55+'Volume & Funnel Build'!AG26*Assumptions!B56+'Volume & Funnel Build'!AG27*Assumptions!B57 -> 39191.528 | AH13: ='Volume & Funnel Build'!AH25*Assumptions!B55+'Volume & Funnel Build'!AH26*Assumptions!B56+'Volume & Funnel Build'!AH27*Assumptions!B57 -> 42187.673 | AI13: ='Volume & Funnel Build'!AI25*Assumptions!B55+'Volume & Funnel Build'!AI26*Assumptions!B56+'Volume & Funnel Build'!AI27*Assumptions!B57 -> 45412.87 | AJ13: ='Volume & Funnel Build'!AJ25*Assumptions!B55+'Volume & Funnel Build'!AJ26*Assumptions!B56+'Volume & Funnel Build'!AJ27*Assumptions!B57 -> 48884.629 | AK13: ='Volume & Funnel Build'!AK25*Assumptions!B55+'Volume & Funnel Build'!AK26*Assumptions!B56+'Volume & Funnel Build'!AK27*Assumptions!B57 -> 52621.8 | AL13: =SUM(B13:M13) -> 9515.1123 | AM13: =SUM(N13:Y13) -> 89320.436 | AN13: =SUM(Z13:AK13) -> 434845.96
A14: TOTAL REVENUE | B14: =SUM(B8:B13) -> 7022.27 | C14: =SUM(C8:C13) -> 7406.6835 | D14: =SUM(D8:D13) -> 7814.9802 | E14: =SUM(E8:E13) -> 8248.7976 | F14: =SUM(F8:F13) -> 8709.8933 | G14: =SUM(G8:G13) -> 9200.1534 | H14: =SUM(H8:H13) -> 9721.6028 | I14: =SUM(I8:I13) -> 10276.416 | ... AK14: =SUM(AK8:AK13) -> 555141.97 | AL14: =SUM(B14:M14) -> 115807.29 | AM14: =SUM(N14:Y14) -> 1144077 | AN14: =SUM(Z14:AK14) -> 4916159.4
A16: COST OF REVENUE
A17: In-House Job COGS | B17: =-B8*(1-Assumptions!B40) -> -1169.4375 | C17: =-C8*(1-Assumptions!B40) -> -1216.2542 | D17: =-D8*(1-Assumptions!B40) -> -1264.9451 | E17: =-E8*(1-Assumptions!B40) -> -1315.5854 | F17: =-F8*(1-Assumptions!B40) -> -1368.2529 | G17: =-G8*(1-Assumptions!B40) -> -1423.0289 | H17: =-H8*(1-Assumptions!B40) -> -1479.9977 | I17: =-I8*(1-Assumptions!B40) -> -1539.2472 | J17: =-J8*(1-Assumptions!B40) -> -1600.8687 | K17: =-K8*(1-Assumptions!B40) -> -1664.9571 | L17: =-L8*(1-Assumptions!B40) -> -1731.6113 | M17: =-M8*(1-Assumptions!B40) -> -1800.9337 | N17: =-N8*(1-Assumptions!B40) -> -1728.8964 | O17: =-O8*(1-Assumptions!B40) -> -2248.4573 | P17: =-P8*(1-Assumptions!B40) -> -2924.1546 | Q17: =-Q8*(1-Assumptions!B40) -> -3802.9097 | R17: =-R8*(1-Assumptions!B40) -> -4945.7448 | S17: =-S8*(1-Assumptions!B40) -> -6432.0199 | T17: =-T8*(1-Assumptions!B40) -> -8364.9445 | U17: =-U8*(1-Assumptions!B40) -> -10878.744 | V17: =-V8*(1-Assumptions!B40) -> -14147.98 | W17: =-W8*(1-Assumptions!B40) -> -18399.673 | X17: =-X8*(1-Assumptions!B40) -> -23929.068 | Y17: =-Y8*(1-Assumptions!B40) -> -31120.135 | Z17: =-Z8*(1-Assumptions!B40) -> -28814.94 | AA17: =-AA8*(1-Assumptions!B40) -> -30184.625 | AB17: =-AB8*(1-Assumptions!B40) -> -31619.417 | AC17: =-AC8*(1-Assumptions!B40) -> -33122.41 | AD17: =-AD8*(1-Assumptions!B40) -> -34696.845 | AE17: =-AE8*(1-Assumptions!B40) -> -36346.12 | AF17: =-AF8*(1-Assumptions!B40) -> -38073.792 | AG17: =-AG8*(1-Assumptions!B40) -> -39883.586 | AH17: =-AH8*(1-Assumptions!B40) -> -41779.406 | AI17: =-AI8*(1-Assumptions!B40) -> -43765.343 | AJ17: =-AJ8*(1-Assumptions!B40) -> -45845.678 | AK17: =-AK8*(1-Assumptions!B40) -> -48024.9 | AL17: =SUM(B17:M17) -> -17575.12 | AM17: =SUM(N17:Y17) -> -128922.73 | AN17: =SUM(Z17:AK17) -> -452157.06
A18: Marketplace Commission COGS | B18: =-B9*(1-Assumptions!B41) -> -12.25125 | C18: =-C9*(1-Assumptions!B41) -> -12.741711 | D18: =-D9*(1-Assumptions!B41) -> -13.251806 | E18: =-E9*(1-Assumptions!B41) -> -13.782323 | F18: =-F9*(1-Assumptions!B41) -> -14.334078 | G18: =-G9*(1-Assumptions!B41) -> -14.907921 | H18: =-H9*(1-Assumptions!B41) -> -15.504738 | I18: =-I9*(1-Assumptions!B41) -> -16.125447 | J18: =-J9*(1-Assumptions!B41) -> -16.771006 | K18: =-K9*(1-Assumptions!B41) -> -17.442408 | L18: =-L9*(1-Assumptions!B41) -> -18.140689 | M18: =-M9*(1-Assumptions!B41) -> -18.866925 | N18: =-N9*(1-Assumptions!B41) -> -36.224496 | O18: =-O9*(1-Assumptions!B41) -> -47.110535 | P18: =-P9*(1-Assumptions!B41) -> -61.268002 | Q18: =-Q9*(1-Assumptions!B41) -> -79.680013 | R18: =-R9*(1-Assumptions!B41) -> -103.62513 | S18: =-S9*(1-Assumptions!B41) -> -134.76613 | T18: =-T9*(1-Assumptions!B41) -> -175.2655 | U18: =-U9*(1-Assumptions!B41) -> -227.93558 | V18: =-V9*(1-Assumptions!B41) -> -296.43386 | W18: =-W9*(1-Assumptions!B41) -> -385.51696 | X18: =-X9*(1-Assumptions!B41) -> -501.37096 | Y18: =-Y9*(1-Assumptions!B41) -> -652.04093 | Z18: =-Z9*(1-Assumptions!B41) -> -905.6124 | AA18: =-AA9*(1-Assumptions!B41) -> -948.65965 | AB18: =-AB9*(1-Assumptions!B41) -> -993.7531 | AC18: =-AC9*(1-Assumptions!B41) -> -1040.99 | AD18: =-AD9*(1-Assumptions!B41) -> -1090.4723 | AE18: =-AE9*(1-Assumptions!B41) -> -1142.3066 | AF18: =-AF9*(1-Assumptions!B41) -> -1196.6049 | AG18: =-AG9*(1-Assumptions!B41) -> -1253.4841 | AH18: =-AH9*(1-Assumptions!B41) -> -1313.0671 | AI18: =-AI9*(1-Assumptions!B41) -> -1375.4822 | AJ18: =-AJ9*(1-Assumptions!B41) -> -1440.8642 | AK18: =-AK9*(1-Assumptions!B41) -> -1509.354 | AL18: =SUM(B18:M18) -> -184.1203 | AM18: =SUM(N18:Y18) -> -2701.2381 | AN18: =SUM(Z18:AK18) -> -14210.651
A19: Booking Fee COGS | B19: =-B10*(1-Assumptions!B42) -> 0 | C19: =-C10*(1-Assumptions!B42) -> 0 | D19: =-D10*(1-Assumptions!B42) -> 0 | E19: =-E10*(1-Assumptions!B42) -> 0 | F19: =-F10*(1-Assumptions!B42) -> 0 | G19: =-G10*(1-Assumptions!B42) -> 0 | H19: =-H10*(1-Assumptions!B42) -> 0 | I19: =-I10*(1-Assumptions!B42) -> 0 | J19: =-J10*(1-Assumptions!B42) -> 0 | K19: =-K10*(1-Assumptions!B42) -> 0 | L19: =-L10*(1-Assumptions!B42) -> 0 | M19: =-M10*(1-Assumptions!B42) -> 0 | N19: =-N10*(1-Assumptions!B42) -> 0 | O19: =-O10*(1-Assumptions!B42) -> 0 | P19: =-P10*(1-Assumptions!B42) -> 0 | Q19: =-Q10*(1-Assumptions!B42) -> 0 | R19: =-R10*(1-Assumptions!B42) -> 0 | S19: =-S10*(1-Assumptions!B42) -> 0 | T19: =-T10*(1-Assumptions!B42) -> 0 | U19: =-U10*(1-Assumptions!B42) -> 0 | V19: =-V10*(1-Assumptions!B42) -> 0 | W19: =-W10*(1-Assumptions!B42) -> 0 | X19: =-X10*(1-Assumptions!B42) -> 0 | Y19: =-Y10*(1-Assumptions!B42) -> 0 | Z19: =-Z10*(1-Assumptions!B42) -> 0 | AA19: =-AA10*(1-Assumptions!B42) -> 0 | AB19: =-AB10*(1-Assumptions!B42) -> 0 | AC19: =-AC10*(1-Assumptions!B42) -> 0 | AD19: =-AD10*(1-Assumptions!B42) -> 0 | AE19: =-AE10*(1-Assumptions!B42) -> 0 | AF19: =-AF10*(1-Assumptions!B42) -> 0 | AG19: =-AG10*(1-Assumptions!B42) -> 0 | AH19: =-AH10*(1-Assumptions!B42) -> 0 | AI19: =-AI10*(1-Assumptions!B42) -> 0 | AJ19: =-AJ10*(1-Assumptions!B42) -> 0 | AK19: =-AK10*(1-Assumptions!B42) -> 0 | AL19: =SUM(B19:M19) -> 0 | AM19: =SUM(N19:Y19) -> 0 | AN19: =SUM(Z19:AK19) -> 0
A20: Emergency Premium COGS | B20: =-B11*(1-Assumptions!B43) -> 17.15175 | C20: =-C11*(1-Assumptions!B43) -> 17.838395 | D20: =-D11*(1-Assumptions!B43) -> 18.552529 | E20: =-E11*(1-Assumptions!B43) -> 19.295252 | F20: =-F11*(1-Assumptions!B43) -> 20.067709 | G20: =-G11*(1-Assumptions!B43) -> 20.87109 | H20: =-H11*(1-Assumptions!B43) -> 21.706633 | I20: =-I11*(1-Assumptions!B43) -> 22.575626 | J20: =-J11*(1-Assumptions!B43) -> 23.479408 | K20: =-K11*(1-Assumptions!B43) -> 24.419372 | L20: =-L11*(1-Assumptions!B43) -> 25.396965 | M20: =-M11*(1-Assumptions!B43) -> 26.413695 | N20: =-N11*(1-Assumptions!B43) -> 31.696434 | O20: =-O11*(1-Assumptions!B43) -> 41.221718 | P20: =-P11*(1-Assumptions!B43) -> 53.609502 | Q20: =-Q11*(1-Assumptions!B43) -> 69.720012 | R20: =-R11*(1-Assumptions!B43) -> 90.671987 | S20: =-S11*(1-Assumptions!B43) -> 117.92037 | T20: =-T11*(1-Assumptions!B43) -> 153.35732 | U20: =-U11*(1-Assumptions!B43) -> 199.44363 | V20: =-V11*(1-Assumptions!B43) -> 259.37963 | W20: =-W11*(1-Assumptions!B43) -> 337.32734 | X20: =-X11*(1-Assumptions!B43) -> 438.69959 | Y20: =-Y11*(1-Assumptions!B43) -> 570.53581 | Z20: =-Z11*(1-Assumptions!B43) -> 633.92868 | AA20: =-AA11*(1-Assumptions!B43) -> 664.06175 | AB20: =-AB11*(1-Assumptions!B43) -> 695.62717 | AC20: =-AC11*(1-Assumptions!B43) -> 728.69301 | AD20: =-AD11*(1-Assumptions!B43) -> 763.3306 | AE20: =-AE11*(1-Assumptions!B43) -> 799.61465 | AF20: =-AF11*(1-Assumptions!B43) -> 837.62342 | AG20: =-AG11*(1-Assumptions!B43) -> 877.43889 | AH20: =-AH11*(1-Assumptions!B43) -> 919.14694 | AI20: =-AI11*(1-Assumptions!B43) -> 962.83754 | AJ20: =-AJ11*(1-Assumptions!B43) -> 1008.6049 | AK20: =-AK11*(1-Assumptions!B43) -> 1056.5478 | AL20: =SUM(B20:M20) -> 257.76842 | AM20: =SUM(N20:Y20) -> 2363.5833 | AN20: =SUM(Z20:AK20) -> 9947.4554
A21: Cleaning Subscription COGS | B21: =-B12*(1-Assumptions!B44) -> -1182.3 | C21: =-C12*(1-Assumptions!B44) -> -1275.8021 | D21: =-D12*(1-Assumptions!B44) -> -1376.6989 | E21: =-E12*(1-Assumptions!B44) -> -1485.575 | F21: =-F12*(1-Assumptions!B44) -> -1603.0617 | G21: =-G12*(1-Assumptions!B44) -> -1729.8397 | H21: =-H12*(1-Assumptions!B44) -> -1866.644 | I21: =-I12*(1-Assumptions!B44) -> -2014.2674 | J21: =-J12*(1-Assumptions!B44) -> -2173.5657 | K21: =-K12*(1-Assumptions!B44) -> -2345.462 | L21: =-L12*(1-Assumptions!B44) -> -2530.9527 | M21: =-M12*(1-Assumptions!B44) -> -2731.113 | N21: =-N12*(1-Assumptions!B44) -> -2731.113 | O21: =-O12*(1-Assumptions!B44) -> -3671.5711 | P21: =-P12*(1-Assumptions!B44) -> -4935.8757 | Q21: =-Q12*(1-Assumptions!B44) -> -6635.5433 | R21: =-R12*(1-Assumptions!B44) -> -8920.491 | S21: =-S12*(1-Assumptions!B44) -> -11992.26 | T21: =-T12*(1-Assumptions!B44) -> -16121.792 | U21: =-U12*(1-Assumptions!B44) -> -21673.327 | V21: =-V12*(1-Assumptions!B44) -> -29136.531 | W21: =-W12*(1-Assumptions!B44) -> -39169.689 | X21: =-X12*(1-Assumptions!B44) -> -52657.762 | Y21: =-Y12*(1-Assumptions!B44) -> -70790.449 | Z21: =-Z12*(1-Assumptions!B44) -> -70790.449 | AA21: =-AA12*(1-Assumptions!B44) -> -75415.862 | AB21: =-AB12*(1-Assumptions!B44) -> -80343.497 | AC21: =-AC12*(1-Assumptions!B44) -> -85593.101 | AD21: =-AD12*(1-Assumptions!B44) -> -91185.712 | AE21: =-AE12*(1-Assumptions!B44) -> -97143.741 | AF21: =-AF12*(1-Assumptions!B44) -> -103491.06 | AG21: =-AG12*(1-Assumptions!B44) -> -110253.12 | AH21: =-AH12*(1-Assumptions!B44) -> -117457 | AI21: =-AI12*(1-Assumptions!B44) -> -125131.59 | AJ21: =-AJ12*(1-Assumptions!B44) -> -133307.62 | AK21: =-AK12*(1-Assumptions!B44) -> -142017.88 | AL21: =SUM(B21:M21) -> -22315.282 | AM21: =SUM(N21:Y21) -> -268436.4 | AN21: =SUM(Z21:AK21) -> -1232130.6
A22: PM Plan COGS | B22: =-B13*(1-Assumptions!B45) -> -268 | C22: =-C13*(1-Assumptions!B45) -> -276.072 | D22: =-D13*(1-Assumptions!B45) -> -284.38712 | E22: =-E13*(1-Assumptions!B45) -> -292.95269 | F22: =-F13*(1-Assumptions!B45) -> -301.77625 | G22: =-G13*(1-Assumptions!B45) -> -310.86557 | H22: =-H13*(1-Assumptions!B45) -> -320.22866 | I22: =-I13*(1-Assumptions!B45) -> -329.87375 | J22: =-J13*(1-Assumptions!B45) -> -339.80935 | K22: =-K13*(1-Assumptions!B45) -> -350.0442 | L22: =-L13*(1-Assumptions!B45) -> -360.58733 | M22: =-M13*(1-Assumptions!B45) -> -371.448 | N22: =-N13*(1-Assumptions!B45) -> -371.448 | O22: =-O13*(1-Assumptions!B45) -> -498.07882 | P22: =-P13*(1-Assumptions!B45) -> -667.87951 | Q22: =-Q13*(1-Assumptions!B45) -> -895.56718 | R22: =-R13*(1-Assumptions!B45) -> -1200.8762 | S22: =-S13*(1-Assumptions!B45) -> -1610.2684 | T22: =-T13*(1-Assumptions!B45) -> -2159.2271 | U22: =-U13*(1-Assumptions!B45) -> -2895.332 | V22: =-V13*(1-Assumptions!B45) -> -3882.3834 | W22: =-W13*(1-Assumptions!B45) -> -5205.9317 | X22: =-X13*(1-Assumptions!B45) -> -6980.6926 | Y22: =-Y13*(1-Assumptions!B45) -> -9360.4896 | Z22: =-Z13*(1-Assumptions!B45) -> -9360.4896 | AA22: =-AA13*(1-Assumptions!B45) -> -10076.088 | AB22: =-AB13*(1-Assumptions!B45) -> -10846.392 | AC22: =-AC13*(1-Assumptions!B45) -> -11675.586 | AD22: =-AD13*(1-Assumptions!B45) -> -12568.171 | AE22: =-AE13*(1-Assumptions!B45) -> -13528.992 | AF22: =-AF13*(1-Assumptions!B45) -> -14563.267 | AG22: =-AG13*(1-Assumptions!B45) -> -15676.611 | AH22: =-AH13*(1-Assumptions!B45) -> -16875.069 | AI22: =-AI13*(1-Assumptions!B45) -> -18165.148 | AJ22: =-AJ13*(1-Assumptions!B45) -> -19553.852 | AK22: =-AK13*(1-Assumptions!B45) -> -21048.72 | AL22: =SUM(B22:M22) -> -3806.0449 | AM22: =SUM(N22:Y22) -> -35728.174 | AN22: =SUM(Z22:AK22) -> -173938.39
A23: TOTAL COST OF REVENUE | B23: =SUM(B17:B22) -> -2614.837 | C23: =SUM(C17:C22) -> -2763.0317 | D23: =SUM(D17:D22) -> -2920.7304 | E23: =SUM(E17:E22) -> -3088.6002 | F23: =SUM(F17:F22) -> -3267.3572 | G23: =SUM(G17:G22) -> -3457.771 | H23: =SUM(H17:H22) -> -3660.6685 | I23: =SUM(I17:I22) -> -3876.9382 | ... AK23: =SUM(AK17:AK22) -> -211544.3 | AL23: =SUM(B23:M23) -> -43622.799 | AM23: =SUM(N23:Y23) -> -433424.96 | AN23: =SUM(Z23:AK23) -> -1862489.3
A25: GROSS PROFIT | B25: =B14+B23 -> 4407.433 | C25: =C14+C23 -> 4643.6519 | D25: =D14+D23 -> 4894.2497 | E25: =E14+E23 -> 5160.1975 | F25: =F14+F23 -> 5442.5361 | G25: =G14+G23 -> 5742.3824 | H25: =H14+H23 -> 6060.9343 | I25: =I14+I23 -> 6399.4774 | ... AK25: =AK14+AK23 -> 343597.67 | AL25: =SUM(B25:M25) -> 72184.491 | AM25: =SUM(N25:Y25) -> 710652.09 | AN25: =SUM(Z25:AK25) -> 3053670.1
A26: Gross Margin % | B26: =IF(B14=0,0,B25/B14) -> 0.62763651 | C26: =IF(C14=0,0,C25/C14) -> 0.62695427 | D26: =IF(D14=0,0,D25/D14) -> 0.62626515 | E26: =IF(E14=0,0,E25/E14) -> 0.62556965 | F26: =IF(F14=0,0,F25/F14) -> 0.62486829 | G26: =IF(G14=0,0,G25/G14) -> 0.6241616 | H26: =IF(H14=0,0,H25/H14) -> 0.62345011 | I26: =IF(I14=0,0,I25/I14) -> 0.62273439 | ... AN26: =IF(AN14=0,0,AN25/AN14) -> 0.62114953
A28: OPERATING EXPENSES
A29: Staff Costs | B29: =-Assumptions!B67/12 -> 0 | C29: =-Assumptions!B67/12 -> 0 | D29: =-Assumptions!B67/12 -> 0 | E29: =-Assumptions!B67/12 -> 0 | F29: =-Assumptions!B67/12 -> 0 | G29: =-Assumptions!B67/12 -> 0 | H29: =-Assumptions!B67/12 -> 0 | I29: =-Assumptions!B67/12 -> 0 | J29: =-Assumptions!B67/12 -> 0 | K29: =-Assumptions!B67/12 -> 0 | L29: =-Assumptions!B67/12 -> 0 | M29: =-Assumptions!B67/12 -> 0 | N29: =-Assumptions!C67/12 -> 0 | O29: =-Assumptions!C67/12 -> 0 | P29: =-Assumptions!C67/12 -> 0 | Q29: =-Assumptions!C67/12 -> 0 | R29: =-Assumptions!C67/12 -> 0 | S29: =-Assumptions!C67/12 -> 0 | T29: =-Assumptions!C67/12 -> 0 | U29: =-Assumptions!C67/12 -> 0 | V29: =-Assumptions!C67/12 -> 0 | W29: =-Assumptions!C67/12 -> 0 | X29: =-Assumptions!C67/12 -> 0 | Y29: =-Assumptions!C67/12 -> 0 | Z29: =-Assumptions!D67/12 -> 0 | AA29: =-Assumptions!D67/12 -> 0 | AB29: =-Assumptions!D67/12 -> 0 | AC29: =-Assumptions!D67/12 -> 0 | AD29: =-Assumptions!D67/12 -> 0 | AE29: =-Assumptions!D67/12 -> 0 | AF29: =-Assumptions!D67/12 -> 0 | AG29: =-Assumptions!D67/12 -> 0 | AH29: =-Assumptions!D67/12 -> 0 | AI29: =-Assumptions!D67/12 -> 0 | AJ29: =-Assumptions!D67/12 -> 0 | AK29: =-Assumptions!D67/12 -> 0 | AL29: =SUM(B29:M29) -> 0 | AM29: =SUM(N29:Y29) -> 0 | AN29: =SUM(Z29:AK29) -> 0
A30: Marketing & User Acquisition | B30: =-'Volume & Funnel Build'!B8*Assumptions!B66 -> -4000 | C30: =-'Volume & Funnel Build'!C8*Assumptions!B66 -> -160.13409 | D30: =-'Volume & Funnel Build'!D8*Assumptions!B66 -> -166.54483 | E30: =-'Volume & Funnel Build'!E8*Assumptions!B66 -> -173.2122 | F30: =-'Volume & Funnel Build'!F8*Assumptions!B66 -> -180.1465 | G30: =-'Volume & Funnel Build'!G8*Assumptions!B66 -> -187.3584 | H30: =-'Volume & Funnel Build'!H8*Assumptions!B66 -> -194.85901 | I30: =-'Volume & Funnel Build'!I8*Assumptions!B66 -> -202.65991 | J30: =-'Volume & Funnel Build'!J8*Assumptions!B66 -> -210.7731 | K30: =-'Volume & Funnel Build'!K8*Assumptions!B66 -> -219.21109 | L30: =-'Volume & Funnel Build'!L8*Assumptions!B66 -> -227.98688 | M30: =-'Volume & Funnel Build'!M8*Assumptions!B66 -> -237.114 | N30: =-'Volume & Funnel Build'!N8*Assumptions!B66 -> 0 | O30: =-'Volume & Funnel Build'!O8*Assumptions!B66 -> -1851.1782 | P30: =-'Volume & Funnel Build'!P8*Assumptions!B66 -> -2407.4868 | Q30: =-'Volume & Funnel Build'!Q8*Assumptions!B66 -> -3130.975 | R30: =-'Volume & Funnel Build'!R8*Assumptions!B66 -> -4071.8829 | S30: =-'Volume & Funnel Build'!S8*Assumptions!B66 -> -5295.5487 | T30: =-'Volume & Funnel Build'!T8*Assumptions!B66 -> -6886.9455 | U30: =-'Volume & Funnel Build'!U8*Assumptions!B66 -> -8956.5825 | V30: =-'Volume & Funnel Build'!V8*Assumptions!B66 -> -11648.178 | W30: =-'Volume & Funnel Build'!W8*Assumptions!B66 -> -15148.642 | X30: =-'Volume & Funnel Build'!X8*Assumptions!B66 -> -19701.05 | Y30: =-'Volume & Funnel Build'!Y8*Assumptions!B66 -> -25621.53 | Z30: =-'Volume & Funnel Build'!Z8*Assumptions!B66 -> 0 | AA30: =-'Volume & Funnel Build'!AA8*Assumptions!B66 -> -5270.554 | AB30: =-'Volume & Funnel Build'!AB8*Assumptions!B66 -> -5521.0837 | AC30: =-'Volume & Funnel Build'!AC8*Assumptions!B66 -> -5783.5221 | AD30: =-'Volume & Funnel Build'!AD8*Assumptions!B66 -> -6058.4352 | AE30: =-'Volume & Funnel Build'!AE8*Assumptions!B66 -> -6346.416 | AF30: =-'Volume & Funnel Build'!AF8*Assumptions!B66 -> -6648.0856 | AG30: =-'Volume & Funnel Build'!AG8*Assumptions!B66 -> -6964.0948 | AH30: =-'Volume & Funnel Build'!AH8*Assumptions!B66 -> -7295.125 | AI30: =-'Volume & Funnel Build'!AI8*Assumptions!B66 -> -7641.8905 | AJ30: =-'Volume & Funnel Build'!AJ8*Assumptions!B66 -> -8005.139 | AK30: =-'Volume & Funnel Build'!AK8*Assumptions!B66 -> -8385.6541 | AL30: =SUM(B30:M30) -> -6160 | AM30: =SUM(N30:Y30) -> -104720 | AN30: =SUM(Z30:AK30) -> -73920
A31: Platform & Tech | B31: =-Assumptions!B68/12 -> -833.33333 | C31: =-Assumptions!B68/12 -> -833.33333 | D31: =-Assumptions!B68/12 -> -833.33333 | E31: =-Assumptions!B68/12 -> -833.33333 | F31: =-Assumptions!B68/12 -> -833.33333 | G31: =-Assumptions!B68/12 -> -833.33333 | H31: =-Assumptions!B68/12 -> -833.33333 | I31: =-Assumptions!B68/12 -> -833.33333 | J31: =-Assumptions!B68/12 -> -833.33333 | K31: =-Assumptions!B68/12 -> -833.33333 | L31: =-Assumptions!B68/12 -> -833.33333 | M31: =-Assumptions!B68/12 -> -833.33333 | N31: =-Assumptions!C68/12 -> -833.33333 | O31: =-Assumptions!C68/12 -> -833.33333 | P31: =-Assumptions!C68/12 -> -833.33333 | Q31: =-Assumptions!C68/12 -> -833.33333 | R31: =-Assumptions!C68/12 -> -833.33333 | S31: =-Assumptions!C68/12 -> -833.33333 | T31: =-Assumptions!C68/12 -> -833.33333 | U31: =-Assumptions!C68/12 -> -833.33333 | V31: =-Assumptions!C68/12 -> -833.33333 | W31: =-Assumptions!C68/12 -> -833.33333 | X31: =-Assumptions!C68/12 -> -833.33333 | Y31: =-Assumptions!C68/12 -> -833.33333 | Z31: =-Assumptions!D68/12 -> -833.33333 | AA31: =-Assumptions!D68/12 -> -833.33333 | AB31: =-Assumptions!D68/12 -> -833.33333 | AC31: =-Assumptions!D68/12 -> -833.33333 | AD31: =-Assumptions!D68/12 -> -833.33333 | AE31: =-Assumptions!D68/12 -> -833.33333 | AF31: =-Assumptions!D68/12 -> -833.33333 | AG31: =-Assumptions!D68/12 -> -833.33333 | AH31: =-Assumptions!D68/12 -> -833.33333 | AI31: =-Assumptions!D68/12 -> -833.33333 | AJ31: =-Assumptions!D68/12 -> -833.33333 | AK31: =-Assumptions!D68/12 -> -833.33333 | AL31: =SUM(B31:M31) -> -10000 | AM31: =SUM(N31:Y31) -> -10000 | AN31: =SUM(Z31:AK31) -> -10000
A32: Admin & G&A | B32: =-Assumptions!B69/12 -> -5000 | C32: =-Assumptions!B69/12 -> -5000 | D32: =-Assumptions!B69/12 -> -5000 | E32: =-Assumptions!B69/12 -> -5000 | F32: =-Assumptions!B69/12 -> -5000 | G32: =-Assumptions!B69/12 -> -5000 | H32: =-Assumptions!B69/12 -> -5000 | I32: =-Assumptions!B69/12 -> -5000 | J32: =-Assumptions!B69/12 -> -5000 | K32: =-Assumptions!B69/12 -> -5000 | L32: =-Assumptions!B69/12 -> -5000 | M32: =-Assumptions!B69/12 -> -5000 | N32: =-Assumptions!C69/12 -> -5000 | O32: =-Assumptions!C69/12 -> -5000 | P32: =-Assumptions!C69/12 -> -5000 | Q32: =-Assumptions!C69/12 -> -5000 | R32: =-Assumptions!C69/12 -> -5000 | S32: =-Assumptions!C69/12 -> -5000 | T32: =-Assumptions!C69/12 -> -5000 | U32: =-Assumptions!C69/12 -> -5000 | V32: =-Assumptions!C69/12 -> -5000 | W32: =-Assumptions!C69/12 -> -5000 | X32: =-Assumptions!C69/12 -> -5000 | Y32: =-Assumptions!C69/12 -> -5000 | Z32: =-Assumptions!D69/12 -> -5000 | AA32: =-Assumptions!D69/12 -> -5000 | AB32: =-Assumptions!D69/12 -> -5000 | AC32: =-Assumptions!D69/12 -> -5000 | AD32: =-Assumptions!D69/12 -> -5000 | AE32: =-Assumptions!D69/12 -> -5000 | AF32: =-Assumptions!D69/12 -> -5000 | AG32: =-Assumptions!D69/12 -> -5000 | AH32: =-Assumptions!D69/12 -> -5000 | AI32: =-Assumptions!D69/12 -> -5000 | AJ32: =-Assumptions!D69/12 -> -5000 | AK32: =-Assumptions!D69/12 -> -5000 | AL32: =SUM(B32:M32) -> -60000 | AM32: =SUM(N32:Y32) -> -60000 | AN32: =SUM(Z32:AK32) -> -60000
A33: TOTAL OPERATING EXPENSES | B33: =SUM(B29:B32) -> -9833.3333 | C33: =SUM(C29:C32) -> -5993.4674 | D33: =SUM(D29:D32) -> -5999.8782 | E33: =SUM(E29:E32) -> -6006.5455 | F33: =SUM(F29:F32) -> -6013.4798 | G33: =SUM(G29:G32) -> -6020.6917 | H33: =SUM(H29:H32) -> -6028.1923 | I33: =SUM(I29:I32) -> -6035.9932 | ... AK33: =SUM(AK29:AK32) -> -14218.987 | AL33: =SUM(B33:M33) -> -76160 | AM33: =SUM(N33:Y33) -> -174720 | AN33: =SUM(Z33:AK33) -> -143920
A35: EBITDA | B35: =B25+B33 -> -5425.9003 | C35: =C25+C33 -> -1349.8156 | D35: =D25+D33 -> -1105.6284 | E35: =E25+E33 -> -846.34807 | F35: =F25+F33 -> -570.94371 | G35: =G25+G33 -> -278.30932 | H35: =H25+H33 -> 32.741995 | I35: =I25+I33 -> 363.48415 | ... AK35: =AK25+AK33 -> 329378.68 | AL35: =SUM(B35:M35) -> -3975.5093 | AM35: =SUM(N35:Y35) -> 535932.09 | AN35: =SUM(Z35:AK35) -> 2909750.1
A36: EBITDA Margin % | B36: =IF(B14=0,0,B35/B14) -> -0.77267042 | C36: =IF(C14=0,0,C35/C14) -> -0.18224291 | D36: =IF(D14=0,0,D35/D14) -> -0.14147552 | E36: =IF(E14=0,0,E35/E14) -> -0.1026026 | F36: =IF(F14=0,0,F35/F14) -> -0.065551172 | G36: =IF(G14=0,0,G35/G14) -> -0.030250509 | H36: =IF(H14=0,0,H35/H14) -> 0.0033679626 | I36: =IF(I14=0,0,I35/I14) -> 0.035370713 | ... AN36: =IF(AN14=0,0,AN35/AN14) -> 0.59187465
A37: Cumulative EBITDA | B37: =B35 -> -5425.9003 | C37: =B37+C35 -> -6775.7159 | D37: =C37+D35 -> -7881.3443 | E37: =D37+E35 -> -8727.6924 | F37: =E37+F35 -> -9298.6361 | G37: =F37+G35 -> -9576.9454 | H37: =G37+H35 -> -9544.2034 | I37: =H37+I35 -> -9180.7193 | J37: =I37+J35 -> -8465.4346 | ... AK37: =AJ37+AK35 -> 3441706.7 | AL37: =M37 -> -3975.5093 | AM37: =Y37 -> 531956.58 | AN37: =AK37 -> 3441706.7
A38: Monthly EBITDA Positive? (1/0) | B38: =IF(B35>0,1,0) -> 0 | C38: =IF(C35>0,1,0) -> 0 | D38: =IF(D35>0,1,0) -> 0 | E38: =IF(E35>0,1,0) -> 0 | F38: =IF(F35>0,1,0) -> 0 | G38: =IF(G35>0,1,0) -> 0 | H38: =IF(H35>0,1,0) -> 1 | I38: =IF(I35>0,1,0) -> 1 | ... AK38: =IF(AK35>0,1,0) -> 1
A39: Cumulative EBITDA Positive? (1/0) | B39: =IF(B37>0,1,0) -> 0 | C39: =IF(C37>0,1,0) -> 0 | D39: =IF(D37>0,1,0) -> 0 | E39: =IF(E37>0,1,0) -> 0 | F39: =IF(F37>0,1,0) -> 0 | G39: =IF(G37>0,1,0) -> 0 | H39: =IF(H37>0,1,0) -> 0 | I39: =IF(I37>0,1,0) -> 0 | ... AK39: =IF(AK37>0,1,0) -> 1

Sheet Annual Summary
A1: ANNUAL SUMMARY
A2: 3-year P&L, revenue mix, graduation metrics and funding requirement — all figures QAR unless noted.
B4: 3-YEAR REVENUE (QAR) | E4: 3-YEAR EBITDA (QAR) | H4: CUMULATIVE BREAKEVEN MONTH | K4: IMPLIED FUNDING REQUIRED (QAR)
B5: ='Monthly P&L'!AL14+'Monthly P&L'!AM14+'Monthly P&L'!AN14 -> 6176043.7 | E5: ='Monthly P&L'!AN37 -> 3441706.7 | H5: ="Month "&MATCH(1,'Monthly P&L'!B39:AK39,0)&" ("&INDEX('Monthly P&L'!B5:AK5,MATCH(1,'Monthly P&L'!B39:AK39,0))&")" -> Month 14 (Y2M2) | K5: =Assumptions!B77+MAX(0,-MIN('Monthly P&L'!B37:AK37)) -> 14576.945
A8: 3-YEAR P&L SUMMARY
B9: FY1 (2026) | C9: FY2 (2027) | D9: FY3 (2028) | E9: 3-Yr Total
A10: Revenue | B10: ='Monthly P&L'!AL14 -> 115807.29 | C10: ='Monthly P&L'!AM14 -> 1144077 | D10: ='Monthly P&L'!AN14 -> 4916159.4 | E10: =SUM(B10:D10) -> 6176043.7
A11: Cost of Revenue | B11: ='Monthly P&L'!AL23 -> -43622.799 | C11: ='Monthly P&L'!AM23 -> -433424.96 | D11: ='Monthly P&L'!AN23 -> -1862489.3 | E11: =SUM(B11:D11) -> -2339537
A12: Gross Profit | B12: ='Monthly P&L'!AL25 -> 72184.491 | C12: ='Monthly P&L'!AM25 -> 710652.09 | D12: ='Monthly P&L'!AN25 -> 3053670.1 | E12: =SUM(B12:D12) -> 3836506.7
A13: Gross Margin % | B13: ='Monthly P&L'!AL26 -> 0.6233156 | C13: ='Monthly P&L'!AM26 -> 0.62115754 | D13: ='Monthly P&L'!AN26 -> 0.62114953 | E13: =E12/E10 -> 0.62119163
A14: Operating Expenses | B14: ='Monthly P&L'!AL33 -> -76160 | C14: ='Monthly P&L'!AM33 -> -174720 | D14: ='Monthly P&L'!AN33 -> -143920 | E14: =SUM(B14:D14) -> -394800
A15: EBITDA | B15: ='Monthly P&L'!AL35 -> -3975.5093 | C15: ='Monthly P&L'!AM35 -> 535932.09 | D15: ='Monthly P&L'!AN35 -> 2909750.1 | E15: =SUM(B15:D15) -> 3441706.7
A16: EBITDA Margin % | B16: ='Monthly P&L'!AL36 -> -0.034328662 | C16: ='Monthly P&L'!AM36 -> 0.46844055 | D16: ='Monthly P&L'!AN36 -> 0.59187465 | E16: =E15/E10 -> 0.55726721
A18: REVENUE MIX BY STREAM (% of Total Revenue)
B19: FY1 (2026) | C19: FY2 (2027) | D19: FY3 (2028)
A20: In-House Job Revenue | B20: ='Monthly P&L'!AL8/'Monthly P&L'!AL14 -> 0.43360507 | C20: ='Monthly P&L'!AM8/'Monthly P&L'!AM14 -> 0.32196315 | D20: ='Monthly P&L'!AN8/'Monthly P&L'!AN14 -> 0.26278182
A21: Marketplace Commission Revenue | B21: ='Monthly P&L'!AL9/'Monthly P&L'!AL14 -> 0.031797705 | C21: ='Monthly P&L'!AM9/'Monthly P&L'!AM14 -> 0.047221262 | D21: ='Monthly P&L'!AN9/'Monthly P&L'!AN14 -> 0.057812001
A22: Booking Fee Revenue | B22: ='Monthly P&L'!AL10/'Monthly P&L'!AL14 -> 0 | C22: ='Monthly P&L'!AM10/'Monthly P&L'!AM14 -> 0 | D22: ='Monthly P&L'!AN10/'Monthly P&L'!AN14 -> 0
A23: Emergency Premium Revenue | B23: ='Monthly P&L'!AL11/'Monthly P&L'!AL14 -> -0.006359541 | C23: ='Monthly P&L'!AM11/'Monthly P&L'!AM14 -> -0.0059026578 | D23: ='Monthly P&L'!AN11/'Monthly P&L'!AN14 -> -0.0057812001
A24: Cleaning Subscription Revenue | B24: ='Monthly P&L'!AL12/'Monthly P&L'!AL14 -> 0.45879344 | C24: ='Monthly P&L'!AM12/'Monthly P&L'!AM14 -> 0.5586462 | D24: ='Monthly P&L'!AN12/'Monthly P&L'!AN14 -> 0.596735
A25: PM Plan Subscription Revenue | B25: ='Monthly P&L'!AL13/'Monthly P&L'!AL14 -> 0.082163328 | C25: ='Monthly P&L'!AM13/'Monthly P&L'!AM14 -> 0.078072046 | D25: ='Monthly P&L'!AN13/'Monthly P&L'!AN14 -> 0.088452374
A27: GRADUATION METRICS (Dec value, end of year)
B28: FY1 (2026) | C28: FY2 (2027) | D28: FY3 (2028)
A29: Cumulative App Downloads (#) | B29: ='Volume & Funnel Build'!AL7 -> 770 | C29: ='Volume & Funnel Build'!AM7 -> 13860 | D29: ='Volume & Funnel Build'!AN7 -> 23100
A30: Download Penetration (% of SAM) | B30: ='Volume & Funnel Build'!AL9 -> 0.01 | C30: ='Volume & Funnel Build'!AM9 -> 0.18 | D30: ='Volume & Funnel Build'!AN9 -> 0.3
A31: Active Customers (#) | B31: ='Volume & Funnel Build'!AL11 -> 115.5 | C31: ='Volume & Funnel Build'!AM11 -> 2494.8 | D31: ='Volume & Funnel Build'!AN11 -> 4620
A32: Jobs / Month (Dec run-rate) | B32: ='Volume & Funnel Build'!M13 -> 31.185 | C32: ='Volume & Funnel Build'!Y13 -> 673.596 | D32: ='Volume & Funnel Build'!AK13 -> 1247.4
A33: Cleaning Subscribers (#) | B33: ='Volume & Funnel Build'!AL17 -> 11.55 | C33: ='Volume & Funnel Build'!AM17 -> 299.376 | D33: ='Volume & Funnel Build'!AN17 -> 600.6
A34: PM Plan Subscribers (#) | B34: ='Volume & Funnel Build'!AL23 -> 6.93 | C34: ='Volume & Funnel Build'!AM23 -> 174.636 | D34: ='Volume & Funnel Build'!AN23 -> 392.7
A36: FUNDING REQUIREMENT
A37: One-Time Capex (Assumptions) | B37: =Assumptions!B77 -> 5000
A38: Peak Cumulative Cash Shortfall (pre-Capex) | B38: =MAX(0,-MIN('Monthly P&L'!B37:AK37)) -> 9576.9454
A39: Implied Funding Required | B39: =B37+B38 -> 14576.945
A41: Funding required = one-time Capex + the largest cumulative EBITDA deficit before the business turns cumulative-cash-positive (Cumulative EBITDA, Monthly P&L row 37).
