Workbook

Sheet Cover
B2: SPORTS MEDIA PLATFORM — MULTI-ROUND REVENUE MODEL
B3: Digital Sports Media · Seed → Series C · Investor Base Case
B5: OVERVIEW
B6: Driver-based revenue model for a multi-vertical sports media platform across four funding stages. Monthly active users convert to subscriptions and in-app advertising; a content site monetises page views through programmatic CPM; an agency arm adds B2B retainers. Each stage upgrades the growth, conversion and pricing drivers. Yellow cells are analyst estimates — change any of them to restate the model.
B8: TABS
B9: 1 · Assumptions — stage-by-stage drivers (Seed / A / B / C)
B10: 2 · Revenue Build — 48-month engine across all four stages
B11: 3 · Stage Summary — revenue by stream and stage, exit run-rates
B13: COLOUR LEGEND
B14: Blue = given / benchmark input
B15: Blue on yellow = analyst estimate — stress-test freely
B16: Black = formula — do not overwrite
B17: Green = cross-tab link — do not overwrite

Sheet Assumptions
A1: SPORTS MEDIA PLATFORM | STAGE ASSUMPTIONS
A2: Columns are funding stages. Each stage runs 12 months in the Revenue Build.
A4: Driver | B4: Seed | C4: Series A | D4: Series B | E4: Series C | F4: Notes
A5: App verticals live | B5: 1 | C5: 2 | D5: 3 | E5: 3 | F5: Rugby first; football and cricket apps launch at A and B.
A6: MAU — start of stage (first vertical seeds at launch) | B6: 25000 | C6: — | D6: — | E6: — | F6: Later stages inherit the prior stage closing MAU.
A7: MAU monthly growth rate | B7: 0.1 | C7: 0.09 | D7: 0.07 | E7: 0.05 | F7: Growth moderates as the base scales.
A8: New-vertical MAU injection at stage start | B8: 0 | C8: 40000 | D8: 60000 | E8: 0 | F8: Users added when a new vertical app launches.
A9: Subscription conversion rate | B9: 0.03 | C9: 0.035 | D9: 0.04 | E9: 0.045 | F9: Share of MAU on the ad-free tier.
A10: Subscription price — $ / month | B10: 2 | C10: 3.5 | D10: 4 | E10: 4.5 | F10: Benchmark pricing steps up with product depth.
A11: In-app ad revenue — $ / MAU / month | B11: 0.1 | C11: 0.12 | D11: 0.14 | E11: 0.16 | F11: Programmatic + sponsorship yield per active user.
A12: Site page views — start of stage | B12: 40000 | C12: — | D12: — | E12: — | F12: Content site traffic; later stages inherit prior closing.
A13: Page view monthly growth rate | B13: 0.15 | C13: 0.12 | D13: 0.09 | E13: 0.06 | F13: SEO compounding early, moderating later.
A14: Ad slots per page | B14: 3 | C14: 3 | D14: 4 | E14: 4 | F14: Display placements per article view.
A15: CPM — $ per 1,000 impressions | B15: 4.5 | C15: 4.5 | D15: 5 | E15: 5.5 | F15: Sports content benchmark CPM.
A16: Agency & B2B income — $ / month | B16: 27500 | C16: 45000 | D16: 70000 | E16: 100000 | F16: Consulting retainers and business development collabs.

Sheet Revenue Build
A1: SPORTS MEDIA PLATFORM | REVENUE BUILD — 48 MONTHS
A2: Stage = ceiling(month / 12). Drivers pull per-stage from Assumptions. Green = cross-tab pull.
A4: Month | B4: 1 | C4: 2 | D4: 3 | E4: 4 | F4: 5 | G4: 6 | H4: 7 | I4: 8 | J4: 9 | K4: 10 | L4: 11 | M4: 12 | N4: 13 | O4: 14 | P4: 15 | Q4: 16 | R4: 17 | S4: 18 | T4: 19 | U4: 20 | V4: 21 | W4: 22 | X4: 23 | Y4: 24 | Z4: 25 | AA4: 26 | AB4: 27 | AC4: 28 | AD4: 29 | AE4: 30 | AF4: 31 | AG4: 32 | AH4: 33 | AI4: 34 | AJ4: 35 | AK4: 36 | AL4: 37 | AM4: 38 | AN4: 39 | AO4: 40 | AP4: 41 | AQ4: 42 | AR4: 43 | AS4: 44 | AT4: 45 | AU4: 46 | AV4: 47 | AW4: 48
A5: Stage | B5: Seed | C5: Seed | D5: Seed | E5: Seed | F5: Seed | G5: Seed | H5: Seed | I5: Seed | J5: Seed | K5: Seed | L5: Seed | M5: Seed | N5: Series A | O5: Series A | P5: Series A | Q5: Series A | R5: Series A | S5: Series A | T5: Series A | U5: Series A | V5: Series A | W5: Series A | X5: Series A | Y5: Series A | Z5: Series B | AA5: Series B | AB5: Series B | AC5: Series B | AD5: Series B | AE5: Series B | AF5: Series B | AG5: Series B | AH5: Series B | AI5: Series B | AJ5: Series B | AK5: Series B | AL5: Series C | AM5: Series C | AN5: Series C | AO5: Series C | AP5: Series C | AQ5: Series C | AR5: Series C | AS5: Series C | AT5: Series C | AU5: Series C | AV5: Series C | AW5: Series C
A7: MAU — platform total | B7: =Assumptions!B6 -> 25000 | C7: =B7*(1+Assumptions!B$7) -> 27500 | D7: =C7*(1+Assumptions!B$7) -> 30250 | E7: =D7*(1+Assumptions!B$7) -> 33275 | F7: =E7*(1+Assumptions!B$7) -> 36602.5 | G7: =F7*(1+Assumptions!B$7) -> 40262.75 | H7: =G7*(1+Assumptions!B$7) -> 44289.025 | I7: =H7*(1+Assumptions!B$7) -> 48717.927 | J7: =I7*(1+Assumptions!B$7) -> 53589.72 | K7: =J7*(1+Assumptions!B$7) -> 58948.692 | L7: =K7*(1+Assumptions!B$7) -> 64843.562 | M7: =L7*(1+Assumptions!B$7) -> 71327.918 | N7: =M7*(1+Assumptions!C$7)+Assumptions!C8 -> 117747.43 | O7: =N7*(1+Assumptions!C$7) -> 128344.7 | P7: =O7*(1+Assumptions!C$7) -> 139895.72 | Q7: =P7*(1+Assumptions!C$7) -> 152486.34 | R7: =Q7*(1+Assumptions!C$7) -> 166210.11 | S7: =R7*(1+Assumptions!C$7) -> 181169.02 | T7: =S7*(1+Assumptions!C$7) -> 197474.23 | U7: =T7*(1+Assumptions!C$7) -> 215246.91 | V7: =U7*(1+Assumptions!C$7) -> 234619.13 | W7: =V7*(1+Assumptions!C$7) -> 255734.85 | X7: =W7*(1+Assumptions!C$7) -> 278750.99 | Y7: =X7*(1+Assumptions!C$7) -> 303838.58 | Z7: =Y7*(1+Assumptions!D$7)+Assumptions!D8 -> 385107.28 | AA7: =Z7*(1+Assumptions!D$7) -> 412064.79 | AB7: =AA7*(1+Assumptions!D$7) -> 440909.32 | AC7: =AB7*(1+Assumptions!D$7) -> 471772.98 | AD7: =AC7*(1+Assumptions!D$7) -> 504797.08 | AE7: =AD7*(1+Assumptions!D$7) -> 540132.88 | AF7: =AE7*(1+Assumptions!D$7) -> 577942.18 | AG7: =AF7*(1+Assumptions!D$7) -> 618398.13 | AH7: =AG7*(1+Assumptions!D$7) -> 661686 | AI7: =AH7*(1+Assumptions!D$7) -> 708004.02 | AJ7: =AI7*(1+Assumptions!D$7) -> 757564.31 | AK7: =AJ7*(1+Assumptions!D$7) -> 810593.81 | AL7: =AK7*(1+Assumptions!E$7)+Assumptions!E8 -> 851123.5 | AM7: =AL7*(1+Assumptions!E$7) -> 893679.67 | AN7: =AM7*(1+Assumptions!E$7) -> 938363.66 | AO7: =AN7*(1+Assumptions!E$7) -> 985281.84 | AP7: =AO7*(1+Assumptions!E$7) -> 1034545.9 | AQ7: =AP7*(1+Assumptions!E$7) -> 1086273.2 | AR7: =AQ7*(1+Assumptions!E$7) -> 1140586.9 | AS7: =AR7*(1+Assumptions!E$7) -> 1197616.2 | AT7: =AS7*(1+Assumptions!E$7) -> 1257497 | AU7: =AT7*(1+Assumptions!E$7) -> 1320371.9 | AV7: =AU7*(1+Assumptions!E$7) -> 1386390.5 | AW7: =AV7*(1+Assumptions!E$7) -> 1455710
A8: Subscribers | B8: =B7*Assumptions!B$9 -> 750 | C8: =C7*Assumptions!B$9 -> 825 | D8: =D7*Assumptions!B$9 -> 907.5 | E8: =E7*Assumptions!B$9 -> 998.25 | F8: =F7*Assumptions!B$9 -> 1098.075 | G8: =G7*Assumptions!B$9 -> 1207.8825 | H8: =H7*Assumptions!B$9 -> 1328.6707 | I8: =I7*Assumptions!B$9 -> 1461.5378 | J8: =J7*Assumptions!B$9 -> 1607.6916 | K8: =K7*Assumptions!B$9 -> 1768.4608 | L8: =L7*Assumptions!B$9 -> 1945.3068 | M8: =M7*Assumptions!B$9 -> 2139.8375 | N8: =N7*Assumptions!C$9 -> 4121.1601 | O8: =O7*Assumptions!C$9 -> 4492.0645 | P8: =P7*Assumptions!C$9 -> 4896.3503 | Q8: =Q7*Assumptions!C$9 -> 5337.0218 | R8: =R7*Assumptions!C$9 -> 5817.3538 | S8: =S7*Assumptions!C$9 -> 6340.9156 | T8: =T7*Assumptions!C$9 -> 6911.598 | U8: =U7*Assumptions!C$9 -> 7533.6418 | V8: =V7*Assumptions!C$9 -> 8211.6696 | W8: =W7*Assumptions!C$9 -> 8950.7198 | X8: =X7*Assumptions!C$9 -> 9756.2846 | Y8: =Y7*Assumptions!C$9 -> 10634.35 | Z8: =Z7*Assumptions!D$9 -> 15404.291 | AA8: =AA7*Assumptions!D$9 -> 16482.592 | AB8: =AB7*Assumptions!D$9 -> 17636.373 | AC8: =AC7*Assumptions!D$9 -> 18870.919 | AD8: =AD7*Assumptions!D$9 -> 20191.883 | AE8: =AE7*Assumptions!D$9 -> 21605.315 | AF8: =AF7*Assumptions!D$9 -> 23117.687 | AG8: =AG7*Assumptions!D$9 -> 24735.925 | AH8: =AH7*Assumptions!D$9 -> 26467.44 | AI8: =AI7*Assumptions!D$9 -> 28320.161 | AJ8: =AJ7*Assumptions!D$9 -> 30302.572 | AK8: =AK7*Assumptions!D$9 -> 32423.752 | AL8: =AL7*Assumptions!E$9 -> 38300.557 | AM8: =AM7*Assumptions!E$9 -> 40215.585 | AN8: =AN7*Assumptions!E$9 -> 42226.365 | AO8: =AO7*Assumptions!E$9 -> 44337.683 | AP8: =AP7*Assumptions!E$9 -> 46554.567 | AQ8: =AQ7*Assumptions!E$9 -> 48882.295 | AR8: =AR7*Assumptions!E$9 -> 51326.41 | AS8: =AS7*Assumptions!E$9 -> 53892.73 | AT8: =AT7*Assumptions!E$9 -> 56587.367 | AU8: =AU7*Assumptions!E$9 -> 59416.735 | AV8: =AV7*Assumptions!E$9 -> 62387.572 | AW8: =AW7*Assumptions!E$9 -> 65506.951
A9: Subscription revenue — $ | B9: =B8*Assumptions!B$10 -> 1500 | C9: =C8*Assumptions!B$10 -> 1650 | D9: =D8*Assumptions!B$10 -> 1815 | E9: =E8*Assumptions!B$10 -> 1996.5 | F9: =F8*Assumptions!B$10 -> 2196.15 | G9: =G8*Assumptions!B$10 -> 2415.765 | H9: =H8*Assumptions!B$10 -> 2657.3415 | I9: =I8*Assumptions!B$10 -> 2923.0757 | J9: =J8*Assumptions!B$10 -> 3215.3832 | K9: =K8*Assumptions!B$10 -> 3536.9215 | L9: =L8*Assumptions!B$10 -> 3890.6137 | M9: =M8*Assumptions!B$10 -> 4279.6751 | N9: =N8*Assumptions!C$10 -> 14424.06 | O9: =O8*Assumptions!C$10 -> 15722.226 | P9: =P8*Assumptions!C$10 -> 17137.226 | Q9: =Q8*Assumptions!C$10 -> 18679.576 | R9: =R8*Assumptions!C$10 -> 20360.738 | S9: =S8*Assumptions!C$10 -> 22193.205 | T9: =T8*Assumptions!C$10 -> 24190.593 | U9: =U8*Assumptions!C$10 -> 26367.746 | V9: =V8*Assumptions!C$10 -> 28740.844 | W9: =W8*Assumptions!C$10 -> 31327.519 | X9: =X8*Assumptions!C$10 -> 34146.996 | Y9: =Y8*Assumptions!C$10 -> 37220.226 | Z9: =Z8*Assumptions!D$10 -> 61617.165 | AA9: =AA8*Assumptions!D$10 -> 65930.366 | AB9: =AB8*Assumptions!D$10 -> 70545.492 | AC9: =AC8*Assumptions!D$10 -> 75483.676 | AD9: =AD8*Assumptions!D$10 -> 80767.533 | AE9: =AE8*Assumptions!D$10 -> 86421.261 | AF9: =AF8*Assumptions!D$10 -> 92470.749 | AG9: =AG8*Assumptions!D$10 -> 98943.702 | AH9: =AH8*Assumptions!D$10 -> 105869.76 | AI9: =AI8*Assumptions!D$10 -> 113280.64 | AJ9: =AJ8*Assumptions!D$10 -> 121210.29 | AK9: =AK8*Assumptions!D$10 -> 129695.01 | AL9: =AL8*Assumptions!E$10 -> 172352.51 | AM9: =AM8*Assumptions!E$10 -> 180970.13 | AN9: =AN8*Assumptions!E$10 -> 190018.64 | AO9: =AO8*Assumptions!E$10 -> 199519.57 | AP9: =AP8*Assumptions!E$10 -> 209495.55 | AQ9: =AQ8*Assumptions!E$10 -> 219970.33 | AR9: =AR8*Assumptions!E$10 -> 230968.84 | AS9: =AS8*Assumptions!E$10 -> 242517.29 | AT9: =AT8*Assumptions!E$10 -> 254643.15 | AU9: =AU8*Assumptions!E$10 -> 267375.31 | AV9: =AV8*Assumptions!E$10 -> 280744.07 | AW9: =AW8*Assumptions!E$10 -> 294781.28
A10: In-app ad revenue — $ | B10: =B7*Assumptions!B$11 -> 2500 | C10: =C7*Assumptions!B$11 -> 2750 | D10: =D7*Assumptions!B$11 -> 3025 | E10: =E7*Assumptions!B$11 -> 3327.5 | F10: =F7*Assumptions!B$11 -> 3660.25 | G10: =G7*Assumptions!B$11 -> 4026.275 | H10: =H7*Assumptions!B$11 -> 4428.9025 | I10: =I7*Assumptions!B$11 -> 4871.7927 | J10: =J7*Assumptions!B$11 -> 5358.972 | K10: =K7*Assumptions!B$11 -> 5894.8692 | L10: =L7*Assumptions!B$11 -> 6484.3562 | M10: =M7*Assumptions!B$11 -> 7132.7918 | N10: =N7*Assumptions!C$11 -> 14129.692 | O10: =O7*Assumptions!C$11 -> 15401.364 | P10: =P7*Assumptions!C$11 -> 16787.487 | Q10: =Q7*Assumptions!C$11 -> 18298.36 | R10: =R7*Assumptions!C$11 -> 19945.213 | S10: =S7*Assumptions!C$11 -> 21740.282 | T10: =T7*Assumptions!C$11 -> 23696.907 | U10: =U7*Assumptions!C$11 -> 25829.629 | V10: =V7*Assumptions!C$11 -> 28154.296 | W10: =W7*Assumptions!C$11 -> 30688.182 | X10: =X7*Assumptions!C$11 -> 33450.119 | Y10: =Y7*Assumptions!C$11 -> 36460.629 | Z10: =Z7*Assumptions!D$11 -> 53915.019 | AA10: =AA7*Assumptions!D$11 -> 57689.07 | AB10: =AB7*Assumptions!D$11 -> 61727.305 | AC10: =AC7*Assumptions!D$11 -> 66048.217 | AD10: =AD7*Assumptions!D$11 -> 70671.592 | AE10: =AE7*Assumptions!D$11 -> 75618.603 | AF10: =AF7*Assumptions!D$11 -> 80911.905 | AG10: =AG7*Assumptions!D$11 -> 86575.739 | AH10: =AH7*Assumptions!D$11 -> 92636.041 | AI10: =AI7*Assumptions!D$11 -> 99120.563 | AJ10: =AJ7*Assumptions!D$11 -> 106059 | AK10: =AK7*Assumptions!D$11 -> 113483.13 | AL10: =AL7*Assumptions!E$11 -> 136179.76 | AM10: =AM7*Assumptions!E$11 -> 142988.75 | AN10: =AN7*Assumptions!E$11 -> 150138.18 | AO10: =AO7*Assumptions!E$11 -> 157645.09 | AP10: =AP7*Assumptions!E$11 -> 165527.35 | AQ10: =AQ7*Assumptions!E$11 -> 173803.72 | AR10: =AR7*Assumptions!E$11 -> 182493.9 | AS10: =AS7*Assumptions!E$11 -> 191618.6 | AT10: =AT7*Assumptions!E$11 -> 201199.53 | AU10: =AU7*Assumptions!E$11 -> 211259.5 | AV10: =AV7*Assumptions!E$11 -> 221822.48 | AW10: =AW7*Assumptions!E$11 -> 232913.6
A12: Site page views | B12: =Assumptions!B12 -> 40000 | C12: =B12*(1+Assumptions!B$13) -> 46000 | D12: =C12*(1+Assumptions!B$13) -> 52900 | E12: =D12*(1+Assumptions!B$13) -> 60835 | F12: =E12*(1+Assumptions!B$13) -> 69960.25 | G12: =F12*(1+Assumptions!B$13) -> 80454.288 | H12: =G12*(1+Assumptions!B$13) -> 92522.431 | I12: =H12*(1+Assumptions!B$13) -> 106400.8 | J12: =I12*(1+Assumptions!B$13) -> 122360.91 | K12: =J12*(1+Assumptions!B$13) -> 140715.05 | L12: =K12*(1+Assumptions!B$13) -> 161822.31 | M12: =L12*(1+Assumptions!B$13) -> 186095.66 | N12: =M12*(1+Assumptions!C$13) -> 208427.13 | O12: =N12*(1+Assumptions!C$13) -> 233438.39 | P12: =O12*(1+Assumptions!C$13) -> 261451 | Q12: =P12*(1+Assumptions!C$13) -> 292825.12 | R12: =Q12*(1+Assumptions!C$13) -> 327964.13 | S12: =R12*(1+Assumptions!C$13) -> 367319.83 | T12: =S12*(1+Assumptions!C$13) -> 411398.21 | U12: =T12*(1+Assumptions!C$13) -> 460765.99 | V12: =U12*(1+Assumptions!C$13) -> 516057.91 | W12: =V12*(1+Assumptions!C$13) -> 577984.86 | X12: =W12*(1+Assumptions!C$13) -> 647343.04 | Y12: =X12*(1+Assumptions!C$13) -> 725024.21 | Z12: =Y12*(1+Assumptions!D$13) -> 790276.39 | AA12: =Z12*(1+Assumptions!D$13) -> 861401.26 | AB12: =AA12*(1+Assumptions!D$13) -> 938927.37 | AC12: =AB12*(1+Assumptions!D$13) -> 1023430.8 | AD12: =AC12*(1+Assumptions!D$13) -> 1115539.6 | AE12: =AD12*(1+Assumptions!D$13) -> 1215938.2 | AF12: =AE12*(1+Assumptions!D$13) -> 1325372.6 | AG12: =AF12*(1+Assumptions!D$13) -> 1444656.2 | AH12: =AG12*(1+Assumptions!D$13) -> 1574675.2 | AI12: =AH12*(1+Assumptions!D$13) -> 1716396 | AJ12: =AI12*(1+Assumptions!D$13) -> 1870871.6 | AK12: =AJ12*(1+Assumptions!D$13) -> 2039250.1 | AL12: =AK12*(1+Assumptions!E$13) -> 2161605.1 | AM12: =AL12*(1+Assumptions!E$13) -> 2291301.4 | AN12: =AM12*(1+Assumptions!E$13) -> 2428779.4 | AO12: =AN12*(1+Assumptions!E$13) -> 2574506.2 | AP12: =AO12*(1+Assumptions!E$13) -> 2728976.6 | AQ12: =AP12*(1+Assumptions!E$13) -> 2892715.2 | AR12: =AQ12*(1+Assumptions!E$13) -> 3066278.1 | AS12: =AR12*(1+Assumptions!E$13) -> 3250254.8 | AT12: =AS12*(1+Assumptions!E$13) -> 3445270.1 | AU12: =AT12*(1+Assumptions!E$13) -> 3651986.3 | AV12: =AU12*(1+Assumptions!E$13) -> 3871105.4 | AW12: =AV12*(1+Assumptions!E$13) -> 4103371.8
A13: Impressions | B13: =B12*Assumptions!B$14 -> 120000 | C13: =C12*Assumptions!B$14 -> 138000 | D13: =D12*Assumptions!B$14 -> 158700 | E13: =E12*Assumptions!B$14 -> 182505 | F13: =F12*Assumptions!B$14 -> 209880.75 | G13: =G12*Assumptions!B$14 -> 241362.86 | H13: =H12*Assumptions!B$14 -> 277567.29 | I13: =I12*Assumptions!B$14 -> 319202.39 | J13: =J12*Assumptions!B$14 -> 367082.74 | K13: =K12*Assumptions!B$14 -> 422145.16 | L13: =L12*Assumptions!B$14 -> 485466.93 | M13: =M12*Assumptions!B$14 -> 558286.97 | N13: =N12*Assumptions!C$14 -> 625281.4 | O13: =O12*Assumptions!C$14 -> 700315.17 | P13: =P12*Assumptions!C$14 -> 784352.99 | Q13: =Q12*Assumptions!C$14 -> 878475.35 | R13: =R12*Assumptions!C$14 -> 983892.39 | S13: =S12*Assumptions!C$14 -> 1101959.5 | T13: =T12*Assumptions!C$14 -> 1234194.6 | U13: =U12*Assumptions!C$14 -> 1382298 | V13: =V12*Assumptions!C$14 -> 1548173.7 | W13: =W12*Assumptions!C$14 -> 1733954.6 | X13: =X12*Assumptions!C$14 -> 1942029.1 | Y13: =Y12*Assumptions!C$14 -> 2175072.6 | Z13: =Z12*Assumptions!D$14 -> 3161105.5 | AA13: =AA12*Assumptions!D$14 -> 3445605 | AB13: =AB12*Assumptions!D$14 -> 3755709.5 | AC13: =AC12*Assumptions!D$14 -> 4093723.4 | AD13: =AD12*Assumptions!D$14 -> 4462158.5 | AE13: =AE12*Assumptions!D$14 -> 4863752.7 | AF13: =AF12*Assumptions!D$14 -> 5301490.5 | AG13: =AG12*Assumptions!D$14 -> 5778624.6 | AH13: =AH12*Assumptions!D$14 -> 6298700.8 | AI13: =AI12*Assumptions!D$14 -> 6865583.9 | AJ13: =AJ12*Assumptions!D$14 -> 7483486.4 | AK13: =AK12*Assumptions!D$14 -> 8157000.2 | AL13: =AL12*Assumptions!E$14 -> 8646420.2 | AM13: =AM12*Assumptions!E$14 -> 9165205.4 | AN13: =AN12*Assumptions!E$14 -> 9715117.8 | AO13: =AO12*Assumptions!E$14 -> 10298025 | AP13: =AP12*Assumptions!E$14 -> 10915906 | AQ13: =AQ12*Assumptions!E$14 -> 11570861 | AR13: =AR12*Assumptions!E$14 -> 12265112 | AS13: =AS12*Assumptions!E$14 -> 13001019 | AT13: =AT12*Assumptions!E$14 -> 13781080 | AU13: =AU12*Assumptions!E$14 -> 14607945 | AV13: =AV12*Assumptions!E$14 -> 15484422 | AW13: =AW12*Assumptions!E$14 -> 16413487
A14: Web ad revenue — $ | B14: =B13/1000*Assumptions!B$15 -> 540 | C14: =C13/1000*Assumptions!B$15 -> 621 | D14: =D13/1000*Assumptions!B$15 -> 714.15 | E14: =E13/1000*Assumptions!B$15 -> 821.2725 | F14: =F13/1000*Assumptions!B$15 -> 944.46338 | G14: =G13/1000*Assumptions!B$15 -> 1086.1329 | H14: =H13/1000*Assumptions!B$15 -> 1249.0528 | I14: =I13/1000*Assumptions!B$15 -> 1436.4107 | J14: =J13/1000*Assumptions!B$15 -> 1651.8723 | K14: =K13/1000*Assumptions!B$15 -> 1899.6532 | L14: =L13/1000*Assumptions!B$15 -> 2184.6012 | M14: =M13/1000*Assumptions!B$15 -> 2512.2914 | N14: =N13/1000*Assumptions!C$15 -> 2813.7663 | O14: =O13/1000*Assumptions!C$15 -> 3151.4183 | P14: =P13/1000*Assumptions!C$15 -> 3529.5885 | Q14: =Q13/1000*Assumptions!C$15 -> 3953.1391 | R14: =R13/1000*Assumptions!C$15 -> 4427.5158 | S14: =S13/1000*Assumptions!C$15 -> 4958.8177 | T14: =T13/1000*Assumptions!C$15 -> 5553.8758 | U14: =U13/1000*Assumptions!C$15 -> 6220.3409 | V14: =V13/1000*Assumptions!C$15 -> 6966.7818 | W14: =W13/1000*Assumptions!C$15 -> 7802.7956 | X14: =X13/1000*Assumptions!C$15 -> 8739.1311 | Y14: =Y13/1000*Assumptions!C$15 -> 9787.8268 | Z14: =Z13/1000*Assumptions!D$15 -> 15805.528 | AA14: =AA13/1000*Assumptions!D$15 -> 17228.025 | AB14: =AB13/1000*Assumptions!D$15 -> 18778.547 | AC14: =AC13/1000*Assumptions!D$15 -> 20468.617 | AD14: =AD13/1000*Assumptions!D$15 -> 22310.792 | AE14: =AE13/1000*Assumptions!D$15 -> 24318.764 | AF14: =AF13/1000*Assumptions!D$15 -> 26507.452 | AG14: =AG13/1000*Assumptions!D$15 -> 28893.123 | AH14: =AH13/1000*Assumptions!D$15 -> 31493.504 | AI14: =AI13/1000*Assumptions!D$15 -> 34327.919 | AJ14: =AJ13/1000*Assumptions!D$15 -> 37417.432 | AK14: =AK13/1000*Assumptions!D$15 -> 40785.001 | AL14: =AL13/1000*Assumptions!E$15 -> 47555.311 | AM14: =AM13/1000*Assumptions!E$15 -> 50408.63 | AN14: =AN13/1000*Assumptions!E$15 -> 53433.148 | AO14: =AO13/1000*Assumptions!E$15 -> 56639.137 | AP14: =AP13/1000*Assumptions!E$15 -> 60037.485 | AQ14: =AQ13/1000*Assumptions!E$15 -> 63639.734 | AR14: =AR13/1000*Assumptions!E$15 -> 67458.118 | AS14: =AS13/1000*Assumptions!E$15 -> 71505.605 | AT14: =AT13/1000*Assumptions!E$15 -> 75795.941 | AU14: =AU13/1000*Assumptions!E$15 -> 80343.698 | AV14: =AV13/1000*Assumptions!E$15 -> 85164.32 | AW14: =AW13/1000*Assumptions!E$15 -> 90274.179
A16: Agency & B2B revenue — $ | B16: =Assumptions!B$16 -> 27500 | C16: =Assumptions!B$16 -> 27500 | D16: =Assumptions!B$16 -> 27500 | E16: =Assumptions!B$16 -> 27500 | F16: =Assumptions!B$16 -> 27500 | G16: =Assumptions!B$16 -> 27500 | H16: =Assumptions!B$16 -> 27500 | I16: =Assumptions!B$16 -> 27500 | J16: =Assumptions!B$16 -> 27500 | K16: =Assumptions!B$16 -> 27500 | L16: =Assumptions!B$16 -> 27500 | M16: =Assumptions!B$16 -> 27500 | N16: =Assumptions!C$16 -> 45000 | O16: =Assumptions!C$16 -> 45000 | P16: =Assumptions!C$16 -> 45000 | Q16: =Assumptions!C$16 -> 45000 | R16: =Assumptions!C$16 -> 45000 | S16: =Assumptions!C$16 -> 45000 | T16: =Assumptions!C$16 -> 45000 | U16: =Assumptions!C$16 -> 45000 | V16: =Assumptions!C$16 -> 45000 | W16: =Assumptions!C$16 -> 45000 | X16: =Assumptions!C$16 -> 45000 | Y16: =Assumptions!C$16 -> 45000 | Z16: =Assumptions!D$16 -> 70000 | AA16: =Assumptions!D$16 -> 70000 | AB16: =Assumptions!D$16 -> 70000 | AC16: =Assumptions!D$16 -> 70000 | AD16: =Assumptions!D$16 -> 70000 | AE16: =Assumptions!D$16 -> 70000 | AF16: =Assumptions!D$16 -> 70000 | AG16: =Assumptions!D$16 -> 70000 | AH16: =Assumptions!D$16 -> 70000 | AI16: =Assumptions!D$16 -> 70000 | AJ16: =Assumptions!D$16 -> 70000 | AK16: =Assumptions!D$16 -> 70000 | AL16: =Assumptions!E$16 -> 100000 | AM16: =Assumptions!E$16 -> 100000 | AN16: =Assumptions!E$16 -> 100000 | AO16: =Assumptions!E$16 -> 100000 | AP16: =Assumptions!E$16 -> 100000 | AQ16: =Assumptions!E$16 -> 100000 | AR16: =Assumptions!E$16 -> 100000 | AS16: =Assumptions!E$16 -> 100000 | AT16: =Assumptions!E$16 -> 100000 | AU16: =Assumptions!E$16 -> 100000 | AV16: =Assumptions!E$16 -> 100000 | AW16: =Assumptions!E$16 -> 100000
A18: TOTAL REVENUE — $ / month | B18: =B9+B10+B14+B16 -> 32040 | C18: =C9+C10+C14+C16 -> 32521 | D18: =D9+D10+D14+D16 -> 33054.15 | E18: =E9+E10+E14+E16 -> 33645.272 | F18: =F9+F10+F14+F16 -> 34300.863 | G18: =G9+G10+G14+G16 -> 35028.173 | H18: =H9+H10+H14+H16 -> 35835.297 | I18: =I9+I10+I14+I16 -> 36731.279 | ... AW18: =AW9+AW10+AW14+AW16 -> 717969.06

Sheet Stage Summary
A1: SPORTS MEDIA PLATFORM | STAGE SUMMARY
A2: Annualised revenue by stream and stage; exit metrics per stage.
A4: Revenue Stream | B4: Seed | C4: Series A | D4: Series B | E4: Series C | F4: 4-Stage Total
A5: Subscriptions | B5: =SUM('Revenue Build'!B9:M9) -> 32076.426 | C5: =SUM('Revenue Build'!N9:Y9) -> 290510.95 | D5: =SUM('Revenue Build'!Z9:AK9) -> 1102235.6 | E5: =SUM('Revenue Build'!AL9:AW9) -> 2743356.7 | F5: =SUM(B5:E5) -> 4168179.7
A6: In-app advertising | B6: =SUM('Revenue Build'!B10:M10) -> 53460.709 | C6: =SUM('Revenue Build'!N10:Y10) -> 284582.16 | D6: =SUM('Revenue Build'!Z10:AK10) -> 964456.19 | E6: =SUM('Revenue Build'!AL10:AW10) -> 2167590.5 | F6: =SUM(B6:E6) -> 3470089.5
A7: Web advertising | B7: =SUM('Revenue Build'!B14:M14) -> 15660.9 | C7: =SUM('Revenue Build'!N14:Y14) -> 67904.998 | D7: =SUM('Revenue Build'!Z14:AK14) -> 318334.71 | E7: =SUM('Revenue Build'!AL14:AW14) -> 802255.3 | F7: =SUM(B7:E7) -> 1204155.9
A8: Agency & B2B | B8: =SUM('Revenue Build'!B16:M16) -> 330000 | C8: =SUM('Revenue Build'!N16:Y16) -> 540000 | D8: =SUM('Revenue Build'!Z16:AK16) -> 840000 | E8: =SUM('Revenue Build'!AL16:AW16) -> 1200000 | F8: =SUM(B8:E8) -> 2910000
A9: TOTAL REVENUE | B9: =SUM('Revenue Build'!B18:M18) -> 431198.04 | C9: =SUM('Revenue Build'!N18:Y18) -> 1182998.1 | D9: =SUM('Revenue Build'!Z18:AK18) -> 3225026.5 | E9: =SUM('Revenue Build'!AL18:AW18) -> 6913202.4 | F9: =SUM(B9:E9) -> 11752425
A11: EXIT METRICS (final month of stage)
A12: MAU — closing | B12: ='Revenue Build'!M7 -> 71327.918 | C12: ='Revenue Build'!Y7 -> 303838.58 | D12: ='Revenue Build'!AK7 -> 810593.81 | E12: ='Revenue Build'!AW7 -> 1455710
A13: Monthly revenue run-rate — closing | B13: ='Revenue Build'!M18 -> 41424.758 | C13: ='Revenue Build'!Y18 -> 128468.68 | D13: ='Revenue Build'!AK18 -> 353963.14 | E13: ='Revenue Build'!AW18 -> 717969.06
A14: Implied ARR at stage exit | B14: =B13*12 -> 497097.1 | C14: =C13*12 -> 1541624.2 | D14: =D13*12 -> 4247557.7 | E14: =E13*12 -> 8615628.7
